Workbook
Name Slicer_Month: #N/A
Name Slicer_Resort: #N/A

Sheet 2026 Payment Summary

Sheet Pivots_Backend
A1: Collection by Resort
A2: Resort | B2: Total Invoice | C2: Total Room Revenue | D2: Deposit Received | E2: Balance (Final Invoice)
A3: (blank)
A4: Resort 1 | B4: 15729669 | C4: 8152194.4 | D4: 5133921.8 | E4: 10603621
A5: Resort 2 | B5: 11586880 | C5: 6380161.8 | D5: 2984393.8 | E5: 8615913.2
A6: Resort 3 | B6: 2006000 | D6: 862637.57 | E6: 1143362.5
A7: Grand Total | B7: 29322548 | C7: 14532356 | D7: 8980953.1 | E7: 20362897
A11: Month | B11: (All) | D11: Month | E11: (All)
A13: Country | B13: Invoice Percentage | D13: Payment Status | E13: Sum of Invoice Amount
A14: UNITED KINGDOM | B14: 0.2363008 | D14: Not paid yet | E14: 13520991
A15: United States | B15: 0.11350125 | D15: Deposit Paid | E15: 8432884.8
A16: Germany | B16: 0.082200773 | D16: Fully Paid | E16: 6227911.3
A17: Russia | B17: 0.076275606 | D17: Credit facility | E17: 589432.94
A18: China | B18: 0.071997551 | D18: Against VCC | E18: 487764.13
A19: Switzerland | B19: 0.04038381 | D19: (blank) | E19: 30773.28
A20: Denmark | B20: 0.038771698 | D20: Payment on Arrival | E20: 19329
A21: Australia | B21: 0.037696999 | D21: Comp | E21: 13461.68
A22: United Arab Emirates | B22: 0.028594582 | D22: Tentative | E22: 0
A23: Unknown | B23: 0.026354 | D23: Grand Total | E23: 29322548
A24: Japan | B24: 0.020616291
A25: Austria | B25: 0.018817522
A26: Singapore | B26: 0.018544649
A27: Sweden | B27: 0.016808676
A28: Italy | B28: 0.016435078 | D28: Month | E28: (All)
A29: Spain | B29: 0.015615795
A30: (blank) | B30: 0.012285495 | D30: Deposit/Full | E30: Sum of Invoice Amount
A31: France | B31: 0.010643585 | D31: Deposit | E31: 22959656
A32: Brazil | B32: 0.0094251249 | D32: Full Payment | E32: 6362892
A33: Chinese Taiwan | B33: 0.0087272183 | D33: Grand Total | E33: 29322548
A34: Argentina | B34: 0.0078760918
A35: Netherlands | B35: 0.00750874
A36: Finland | B36: 0.0071381041
A37: Turkey | B37: 0.0068708947
A38: Kazakhstan | B38: 0.0063839097 | D38: Month | E38: (All)
A39: Ukraine | B39: 0.0051743852
A40: India | B40: 0.0047798472 | D40: Country | E40: Invoice Percentage
A41: Saudi Arabia | B41: 0.0047457335 | D41: UNITED KINGDOM | E41: 0.31419759
A42: Bermuda | B42: 0.0047341714 | D42: United States | E42: 0.15091704
A43: Korea (South) | B43: 0.004714769 | D43: Germany | E43: 0.10929834
A44: Thailand | B44: 0.0041502853 | D44: Russia | E44: 0.10141993
A45: Portugal | B45: 0.0040960628 | D45: China | E45: 0.095731613
A46: Malaysia | B46: 0.0034492596 | D46: Switzerland | E46: 0.053696372
A47: Ireland | B47: 0.0032519125 | D47: Denmark | E47: 0.051552825
A48: Greece | B48: 0.0029024081 | D48: Australia | E48: 0.050123851
A49: Canada | B49: 0.0026586059 | D49: United Arab Emirates | E49: 0.038020814
A50: Poland | B50: 0.0024146946 | D50: Unknown | E50: 0.035041621
A51: Hong Kong SAR of China | B51: 0.0023194741 | D51: Grand Total | E51: 1
A52: Slovakia | B52: 0.0019432554
A53: Kuwait | B53: 0.0017859567
A54: Do Not Use | B54: 0.0017050476
A55: Cyprus | B55: 0.001586444
A56: Pakistan | B56: 0.0015562276
A57: Vietnam | B57: 0.0012412291
A58: Bulgaria | B58: 0.00087113848
A59: Norway | B59: 0.00086791434
A60: Luxembourg | B60: 0.00079410425
A61: Indonesia | B61: 0.00070835113
A62: Philippines | B62: 0.00067763551
A63: Qatar | B63: 0.00054260155
... A67: Grand Total | B67: 1

Sheet Dashboard_Data
A1: Collection by Resort
A2: Resort | B2: Total Invoice | C2: Total Room Revenue | D2: Deposit Received | E2: Balance (Final Invoice)
A3: Resort 1 | B3: =IFERROR(GETPIVOTDATA("Total Invoice",Pivots_Backend!$A$2,"Resort",$A3),0) -> 15729669 | C3: =IFERROR(GETPIVOTDATA("Total Room Revenue",Pivots_Backend!$A$2,"Resort",$A3),0) -> 8152194.4 | D3: =IFERROR(GETPIVOTDATA("Deposit Received",Pivots_Backend!$A$2,"Resort",$A3),0) -> 5133921.8 | E3: =IFERROR(GETPIVOTDATA("Balance (Final Invoice)",Pivots_Backend!$A$2,"Resort",$A3),0) -> 10603621
A4: Resort 2 | B4: =IFERROR(GETPIVOTDATA("Total Invoice",Pivots_Backend!$A$2,"Resort",$A4),0) -> 11586880 | C4: =IFERROR(GETPIVOTDATA("Total Room Revenue",Pivots_Backend!$A$2,"Resort",$A4),0) -> 6380161.8 | D4: =IFERROR(GETPIVOTDATA("Deposit Received",Pivots_Backend!$A$2,"Resort",$A4),0) -> 2984393.8 | E4: =IFERROR(GETPIVOTDATA("Balance (Final Invoice)",Pivots_Backend!$A$2,"Resort",$A4),0) -> 8615913.2
A5: Resort 3 | B5: =IFERROR(GETPIVOTDATA("Total Invoice",Pivots_Backend!$A$2,"Resort",$A5),0) -> 2006000 | C5: =IFERROR(GETPIVOTDATA("Total Room Revenue",Pivots_Backend!$A$2,"Resort",$A5),0) -> 0 | D5: =IFERROR(GETPIVOTDATA("Deposit Received",Pivots_Backend!$A$2,"Resort",$A5),0) -> 862637.57 | E5: =IFERROR(GETPIVOTDATA("Balance (Final Invoice)",Pivots_Backend!$A$2,"Resort",$A5),0) -> 1143362.5
A6: Grand Total | B6: =IFERROR(GETPIVOTDATA("Total Invoice",Pivots_Backend!$A$2),0) -> 29322548 | C6: =IFERROR(GETPIVOTDATA("Total Room Revenue",Pivots_Backend!$A$2),0) -> 14532356 | D6: =IFERROR(GETPIVOTDATA("Deposit Received",Pivots_Backend!$A$2),0) -> 8980953.1 | E6: =IFERROR(GETPIVOTDATA("Balance (Final Invoice)",Pivots_Backend!$A$2),0) -> 20362897

Sheet Data_Consolidated
A1: Resort | B1: Due Date | C1: Invoice Amount | D1: Payment Received | E1: Balance | F1: Payment Status | G1: Arrival | H1: Departure | I1: No of nights | J1: Month | K1: Month Number | L1: Year | M1: Payment Type | N1: Room Revenue | O1: Date Entered | P1: Country
A2: Resort 1 | B2: 90 days pta | C2: 199999.97 | D2: 199999.97 | F2: Fully Paid | G2: 46023 | H2: 46030 | I2: 7 | J2: =TEXT(tblPayments[[#This Row],[Arrival]],"mmm") -> Jan | K2: =MONTH(tblPayments[[#This Row],[Arrival]]) -> 1 | L2: =YEAR(tblPayments[[#This Row],[Arrival]]) -> 2026 | M2: =IF(tblPayments[[#This Row],[Balance]]=0,"Full Payment","Deposit") -> Full Payment | N2: 137553.57 | O2: 45933 | P2: Russia
A3: Resort 1 | B3: 90 days pta | C3: 209974.09 | D3: 209974.09 | F3: Fully Paid | G3: 46023 | H3: 46030 | I3: 7 | J3: =TEXT(tblPayments[[#This Row],[Arrival]],"mmm") -> Jan | K3: =MONTH(tblPayments[[#This Row],[Arrival]]) -> 1 | L3: =YEAR(tblPayments[[#This Row],[Arrival]]) -> 2026 | M3: =IF(tblPayments[[#This Row],[Balance]]=0,"Full Payment","Deposit") -> Full Payment | N3: 149217.09 | O3: 45861 | P3: UNITED KINGDOM
A4: Resort 1 | B4: 90 days pta | C4: 136440 | D4: 136440 | F4: Fully Paid | G4: 46024 | H4: 46034 | I4: 10 | J4: =TEXT(tblPayments[[#This Row],[Arrival]],"mmm") -> Jan | K4: =MONTH(tblPayments[[#This Row],[Arrival]]) -> 1 | L4: =YEAR(tblPayments[[#This Row],[Arrival]]) -> 2026 | M4: =IF(tblPayments[[#This Row],[Balance]]=0,"Full Payment","Deposit") -> Full Payment | N4: 95268.04 | O4: 45895 | P4: Russia
A5: Resort 1 | B5: 90 days pta | C5: 131512 | D5: 131512 | F5: Fully Paid | G5: 46024 | H5: 46033 | I5: 9 | J5: =TEXT(tblPayments[[#This Row],[Arrival]],"mmm") -> Jan | K5: =MONTH(tblPayments[[#This Row],[Arrival]]) -> 1 | L5: =YEAR(tblPayments[[#This Row],[Arrival]]) -> 2026 | M5: =IF(tblPayments[[#This Row],[Balance]]=0,"Full Payment","Deposit") -> Full Payment | N5: 90370.98 | O5: 45973 | P5: Russia
A6: Resort 1 | B6: 90 days pta | C6: 65778 | D6: 65778 | F6: Fully Paid | G6: 46025 | H6: 46032 | I6: 7 | J6: =TEXT(tblPayments[[#This Row],[Arrival]],"mmm") -> Jan | K6: =MONTH(tblPayments[[#This Row],[Arrival]]) -> 1 | L6: =YEAR(tblPayments[[#This Row],[Arrival]]) -> 2026 | M6: =IF(tblPayments[[#This Row],[Balance]]=0,"Full Payment","Deposit") -> Full Payment | N6: 36985.27 | O6: 45736 | P6: UNITED KINGDOM
A7: Resort 1 | B7: 90 days pta | C7: 116300 | D7: 116300 | F7: Fully Paid | G7: 46025 | H7: 46034 | I7: 9 | J7: =TEXT(tblPayments[[#This Row],[Arrival]],"mmm") -> Jan | K7: =MONTH(tblPayments[[#This Row],[Arrival]]) -> 1 | L7: =YEAR(tblPayments[[#This Row],[Arrival]]) -> 2026 | M7: =IF(tblPayments[[#This Row],[Balance]]=0,"Full Payment","Deposit") -> Full Payment | N7: 84335.67 | O7: 45901 | P7: Russia
A8: Resort 1 | B8: 90 days pta | C8: 78492.39 | D8: 78824.54 | F8: Fully Paid | G8: 46025 | H8: 46032 | I8: 7 | J8: =TEXT(tblPayments[[#This Row],[Arrival]],"mmm") -> Jan | K8: =MONTH(tblPayments[[#This Row],[Arrival]]) -> 1 | L8: =YEAR(tblPayments[[#This Row],[Arrival]]) -> 2026 | M8: =IF(tblPayments[[#This Row],[Balance]]=0,"Full Payment","Deposit") -> Full Payment | N8: 57379.84 | O8: 45833 | P8: Russia
A9: Resort 1 | B9: 90 days pta | C9: 20030.88 | D9: 20030.88 | F9: Fully Paid | G9: 46026 | H9: 46030 | I9: 4 | J9: =TEXT(tblPayments[[#This Row],[Arrival]],"mmm") -> Jan | K9: =MONTH(tblPayments[[#This Row],[Arrival]]) -> 1 | L9: =YEAR(tblPayments[[#This Row],[Arrival]]) -> 2026 | M9: =IF(tblPayments[[#This Row],[Balance]]=0,"Full Payment","Deposit") -> Full Payment | N9: 11604.76 | O9: 45912 | P9: India
A10: Resort 1 | B10: 90 days pta | C10: 85106 | D10: 85106 | F10: Fully Paid | G10: 46026 | H10: 46031 | I10: 5 | J10: =TEXT(tblPayments[[#This Row],[Arrival]],"mmm") -> Jan | K10: =MONTH(tblPayments[[#This Row],[Arrival]]) -> 1 | L10: =YEAR(tblPayments[[#This Row],[Arrival]]) -> 2026 | M10: =IF(tblPayments[[#This Row],[Balance]]=0,"Full Payment","Deposit") -> Full Payment | N10: 59803.1 | O10: 45933 | P10: Greece
A11: Resort 1 | B11: 90 days pta | C11: 0 | D11: 0 | F11: Comp | G11: 46026 | H11: 46028 | I11: 2 | J11: =TEXT(tblPayments[[#This Row],[Arrival]],"mmm") -> Jan | K11: =MONTH(tblPayments[[#This Row],[Arrival]]) -> 1 | L11: =YEAR(tblPayments[[#This Row],[Arrival]]) -> 2026 | M11: =IF(tblPayments[[#This Row],[Balance]]=0,"Full Payment","Deposit") -> Full Payment | N11: 0 | O11: 45973 | P11: Thailand
A12: Resort 1 | B12: 90 days pta | C12: 0 | D12: 0 | F12: Tentative | G12: 46026 | H12: 46033 | I12: 7 | J12: =TEXT(tblPayments[[#This Row],[Arrival]],"mmm") -> Jan | K12: =MONTH(tblPayments[[#This Row],[Arrival]]) -> 1 | L12: =YEAR(tblPayments[[#This Row],[Arrival]]) -> 2026 | M12: =IF(tblPayments[[#This Row],[Balance]]=0,"Full Payment","Deposit") -> Full Payment | N12: 22696.94 | O12: 46001 | P12: Unknown
A13: Resort 1 | B13: 90 days pta | C13: 0 | D13: 0 | F13: Tentative | G13: 46026 | H13: 46033 | I13: 7 | J13: =TEXT(tblPayments[[#This Row],[Arrival]],"mmm") -> Jan | K13: =MONTH(tblPayments[[#This Row],[Arrival]]) -> 1 | L13: =YEAR(tblPayments[[#This Row],[Arrival]]) -> 2026 | M13: =IF(tblPayments[[#This Row],[Balance]]=0,"Full Payment","Deposit") -> Full Payment | N13: 22696.94 | O13: 46001 | P13: Unknown
A14: Resort 1 | B14: 90 days pta | C14: 18682.88 | D14: 18682.88 | F14: Fully Paid | G14: 46026 | H14: 46030 | I14: 4 | J14: =TEXT(tblPayments[[#This Row],[Arrival]],"mmm") -> Jan | K14: =MONTH(tblPayments[[#This Row],[Arrival]]) -> 1 | L14: =YEAR(tblPayments[[#This Row],[Arrival]]) -> 2026 | M14: =IF(tblPayments[[#This Row],[Balance]]=0,"Full Payment","Deposit") -> Full Payment | N14: 11766.56 | O14: 45837 | P14: Unknown
A15: Resort 1 | B15: 90 days pta | C15: 63049.9 | D15: 2600 | E15: 60449.9 | F15: Against VCC | G15: 46027 | H15: 46036 | I15: 9 | J15: =TEXT(tblPayments[[#This Row],[Arrival]],"mmm") -> Jan | K15: =MONTH(tblPayments[[#This Row],[Arrival]]) -> 1 | L15: =YEAR(tblPayments[[#This Row],[Arrival]]) -> 2026 | M15: =IF(tblPayments[[#This Row],[Balance]]=0,"Full Payment","Deposit") -> Deposit | N15: 45073.17 | O15: 45938 | P15: France
A16: Resort 1 | B16: 90 days pta | C16: 43204 | D16: 43204 | F16: Fully Paid | G16: 46027 | H16: 46033 | I16: 6 | J16: =TEXT(tblPayments[[#This Row],[Arrival]],"mmm") -> Jan | K16: =MONTH(tblPayments[[#This Row],[Arrival]]) -> 1 | L16: =YEAR(tblPayments[[#This Row],[Arrival]]) -> 2026 | M16: =IF(tblPayments[[#This Row],[Balance]]=0,"Full Payment","Deposit") -> Full Payment | N16: 30396.3 | O16: 45975 | P16: Germany
A17: Resort 1 | B17: 90 days pta | C17: 30367.55 | D17: 30367.55 | F17: Fully Paid | G17: 46027 | H17: 46030 | I17: 3 | J17: =TEXT(tblPayments[[#This Row],[Arrival]],"mmm") -> Jan | K17: =MONTH(tblPayments[[#This Row],[Arrival]]) -> 1 | L17: =YEAR(tblPayments[[#This Row],[Arrival]]) -> 2026 | M17: =IF(tblPayments[[#This Row],[Balance]]=0,"Full Payment","Deposit") -> Full Payment | N17: 21402.3 | O17: 45961 | P17: Japan
A18: Resort 1 | B18: 90 days pta | C18: 56372.1 | D18: 56372.1 | F18: Deposit Paid | G18: 46028 | H18: 46035 | I18: 7 | J18: =TEXT(tblPayments[[#This Row],[Arrival]],"mmm") -> Jan | K18: =MONTH(tblPayments[[#This Row],[Arrival]]) -> 1 | L18: =YEAR(tblPayments[[#This Row],[Arrival]]) -> 2026 | M18: =IF(tblPayments[[#This Row],[Balance]]=0,"Full Payment","Deposit") -> Full Payment | N18: 38085.53 | O18: 45976 | P18: Russia
A19: Resort 1 | B19: 90 days pta | C19: 0 | D19: 0 | F19: Comp | G19: 46028 | H19: 46033 | I19: 5 | J19: =TEXT(tblPayments[[#This Row],[Arrival]],"mmm") -> Jan | K19: =MONTH(tblPayments[[#This Row],[Arrival]]) -> 1 | L19: =YEAR(tblPayments[[#This Row],[Arrival]]) -> 2026 | M19: =IF(tblPayments[[#This Row],[Balance]]=0,"Full Payment","Deposit") -> Full Payment | N19: 0 | O19: 45975 | P19: Russia
A20: Resort 1 | B20: 90 days pta | F20: Comp | G20: 46029 | H20: 46036 | I20: 7 | J20: =TEXT(tblPayments[[#This Row],[Arrival]],"mmm") -> Jan | K20: =MONTH(tblPayments[[#This Row],[Arrival]]) -> 1 | L20: =YEAR(tblPayments[[#This Row],[Arrival]]) -> 2026 | M20: =IF(tblPayments[[#This Row],[Balance]]=0,"Full Payment","Deposit") -> Full Payment | N20: 10040.38
A21: Resort 1 | B21: 90 days pta | C21: 19000 | D21: 11017.78 | E21: 7982.22 | F21: Deposit Paid | G21: 46029 | H21: 46045 | I21: 16 | J21: =TEXT(tblPayments[[#This Row],[Arrival]],"mmm") -> Jan | K21: =MONTH(tblPayments[[#This Row],[Arrival]]) -> 1 | L21: =YEAR(tblPayments[[#This Row],[Arrival]]) -> 2026 | M21: =IF(tblPayments[[#This Row],[Balance]]=0,"Full Payment","Deposit") -> Deposit | N21: 0 | O21: 45743 | P21: Switzerland
A22: Resort 1 | B22: 90 days pta | C22: 52368.8 | E22: 52368.8 | F22: Not paid yet | G22: 46030 | H22: 46037 | I22: 7 | J22: =TEXT(tblPayments[[#This Row],[Arrival]],"mmm") -> Jan | K22: =MONTH(tblPayments[[#This Row],[Arrival]]) -> 1 | L22: =YEAR(tblPayments[[#This Row],[Arrival]]) -> 2026 | M22: =IF(tblPayments[[#This Row],[Balance]]=0,"Full Payment","Deposit") -> Deposit | N22: 37832.76 | O22: 45995 | P22: Kuwait
A23: Resort 1 | B23: 90 days pta | F23: Tentative | G23: 46030 | H23: 46046 | I23: 16 | J23: =TEXT(tblPayments[[#This Row],[Arrival]],"mmm") -> Jan | K23: =MONTH(tblPayments[[#This Row],[Arrival]]) -> 1 | L23: =YEAR(tblPayments[[#This Row],[Arrival]]) -> 2026 | M23: =IF(tblPayments[[#This Row],[Balance]]=0,"Full Payment","Deposit") -> Full Payment | N23: 10622.68 | O23: 45932 | P23: Switzerland
A24: Resort 1 | B24: 90 days pta | C24: 0 | D24: 0 | F24: Comp | G24: 46031 | H24: 46038 | I24: 7 | J24: =TEXT(tblPayments[[#This Row],[Arrival]],"mmm") -> Jan | K24: =MONTH(tblPayments[[#This Row],[Arrival]]) -> 1 | L24: =YEAR(tblPayments[[#This Row],[Arrival]]) -> 2026 | M24: =IF(tblPayments[[#This Row],[Balance]]=0,"Full Payment","Deposit") -> Full Payment | N24: 0 | O24: 45674 | P24: UNITED KINGDOM
A25: Resort 1 | B25: 90 days pta | C25: 67954.74 | D25: 67954.74 | F25: Fully Paid | G25: 46031 | H25: 46039 | I25: 8 | J25: =TEXT(tblPayments[[#This Row],[Arrival]],"mmm") -> Jan | K25: =MONTH(tblPayments[[#This Row],[Arrival]]) -> 1 | L25: =YEAR(tblPayments[[#This Row],[Arrival]]) -> 2026 | M25: =IF(tblPayments[[#This Row],[Balance]]=0,"Full Payment","Deposit") -> Full Payment | N25: 49406.1 | O25: 45980 | P25: Argentina
A26: Resort 1 | B26: 90 days pta | C26: 157003.12 | D26: 157003.12 | F26: Fully Paid | G26: 46032 | H26: 46040 | I26: 8 | J26: =TEXT(tblPayments[[#This Row],[Arrival]],"mmm") -> Jan | K26: =MONTH(tblPayments[[#This Row],[Arrival]]) -> 1 | L26: =YEAR(tblPayments[[#This Row],[Arrival]]) -> 2026 | M26: =IF(tblPayments[[#This Row],[Balance]]=0,"Full Payment","Deposit") -> Full Payment | N26: 107244.08 | O26: 45792 | P26: Finland
A27: Resort 1 | B27: 30 days pta | C27: 33897 | D27: 33897 | F27: Fully Paid | G27: 46034 | H27: 46040 | I27: 6 | J27: =TEXT(tblPayments[[#This Row],[Arrival]],"mmm") -> Jan | K27: =MONTH(tblPayments[[#This Row],[Arrival]]) -> 1 | L27: =YEAR(tblPayments[[#This Row],[Arrival]]) -> 2026 | M27: =IF(tblPayments[[#This Row],[Balance]]=0,"Full Payment","Deposit") -> Full Payment | N27: 20535.72 | O27: 45966 | P27: Russia
A28: Resort 1 | B28: 30 days pta | C28: 41700 | D28: 41700 | F28: Fully Paid | G28: 46034 | H28: 46043 | I28: 9 | J28: =TEXT(tblPayments[[#This Row],[Arrival]],"mmm") -> Jan | K28: =MONTH(tblPayments[[#This Row],[Arrival]]) -> 1 | L28: =YEAR(tblPayments[[#This Row],[Arrival]]) -> 2026 | M28: =IF(tblPayments[[#This Row],[Balance]]=0,"Full Payment","Deposit") -> Full Payment | N28: 10003.08 | O28: 45911 | P28: Sweden
A29: Resort 1 | B29: 30 days pta | C29: 58243.22 | E29: 58243.22 | F29: Not paid yet | G29: 46034 | H29: 46048 | I29: 14 | J29: =TEXT(tblPayments[[#This Row],[Arrival]],"mmm") -> Jan | K29: =MONTH(tblPayments[[#This Row],[Arrival]]) -> 1 | L29: =YEAR(tblPayments[[#This Row],[Arrival]]) -> 2026 | M29: =IF(tblPayments[[#This Row],[Balance]]=0,"Full Payment","Deposit") -> Deposit | N29: 34161.12 | O29: 45777 | P29: Sweden
A30: Resort 1 | B30: 30 days pta | F30: Tentative | G30: 46034 | H30: 46038 | I30: 4 | J30: =TEXT(tblPayments[[#This Row],[Arrival]],"mmm") -> Jan | K30: =MONTH(tblPayments[[#This Row],[Arrival]]) -> 1 | L30: =YEAR(tblPayments[[#This Row],[Arrival]]) -> 2026 | M30: =IF(tblPayments[[#This Row],[Balance]]=0,"Full Payment","Deposit") -> Full Payment | O30: 46002
A31: Resort 1 | B31: 30 days pta | C31: 29085 | E31: 29085 | F31: Not paid yet | G31: 46035 | H31: 46040 | I31: 5 | J31: =TEXT(tblPayments[[#This Row],[Arrival]],"mmm") -> Jan | K31: =MONTH(tblPayments[[#This Row],[Arrival]]) -> 1 | L31: =YEAR(tblPayments[[#This Row],[Arrival]]) -> 2026 | M31: =IF(tblPayments[[#This Row],[Balance]]=0,"Full Payment","Deposit") -> Deposit | N31: 19570.7 | O31: 45998 | P31: Switzerland
A32: Resort 1 | B32: 30 days pta | C32: 43861.8 | D32: 18861.8 | E32: 25000 | F32: Deposit Paid | G32: 46035 | H32: 46041 | I32: 6 | J32: =TEXT(tblPayments[[#This Row],[Arrival]],"mmm") -> Jan | K32: =MONTH(tblPayments[[#This Row],[Arrival]]) -> 1 | L32: =YEAR(tblPayments[[#This Row],[Arrival]]) -> 2026 | M32: =IF(tblPayments[[#This Row],[Balance]]=0,"Full Payment","Deposit") -> Deposit | N32: 32644.74 | O32: 45976 | P32: Russia
A33: Resort 1 | B33: 30 days pta | C33: 127800.88 | D33: 50000 | E33: 77800.88 | F33: Deposit Paid | G33: 46035 | H33: 46049 | I33: 14 | J33: =TEXT(tblPayments[[#This Row],[Arrival]],"mmm") -> Jan | K33: =MONTH(tblPayments[[#This Row],[Arrival]]) -> 1 | L33: =YEAR(tblPayments[[#This Row],[Arrival]]) -> 2026 | M33: =IF(tblPayments[[#This Row],[Balance]]=0,"Full Payment","Deposit") -> Deposit | N33: 88943.12 | O33: 45917 | P33: Russia
A34: Resort 1 | B34: 30 days pta | C34: 103950 | D34: 103950 | F34: Fully Paid | G34: 46035 | H34: 46045 | I34: 10 | J34: =TEXT(tblPayments[[#This Row],[Arrival]],"mmm") -> Jan | K34: =MONTH(tblPayments[[#This Row],[Arrival]]) -> 1 | L34: =YEAR(tblPayments[[#This Row],[Arrival]]) -> 2026 | M34: =IF(tblPayments[[#This Row],[Balance]]=0,"Full Payment","Deposit") -> Full Payment | N34: 0 | O34: 45555 | P34: United States
A35: Resort 1 | B35: 30 days pta | C35: 91560 | E35: 91560 | F35: Not paid yet | G35: 46036 | H35: 46066 | I35: 30 | J35: =TEXT(tblPayments[[#This Row],[Arrival]],"mmm") -> Jan | K35: =MONTH(tblPayments[[#This Row],[Arrival]]) -> 1 | L35: =YEAR(tblPayments[[#This Row],[Arrival]]) -> 2026 | M35: =IF(tblPayments[[#This Row],[Balance]]=0,"Full Payment","Deposit") -> Deposit | N35: 47179.5 | O35: 45776 | P35: Denmark
A36: Resort 1 | B36: 30 days pta | C36: 136400.34 | E36: 136400.34 | F36: Not paid yet | G36: 46036 | H36: 46054 | I36: 18 | J36: =TEXT(tblPayments[[#This Row],[Arrival]],"mmm") -> Jan | K36: =MONTH(tblPayments[[#This Row],[Arrival]]) -> 1 | L36: =YEAR(tblPayments[[#This Row],[Arrival]]) -> 2026 | M36: =IF(tblPayments[[#This Row],[Balance]]=0,"Full Payment","Deposit") -> Deposit | N36: 87639.12 | O36: 45861 | P36: Argentina
A37: Resort 1 | B37: 30 days pta | F37: Tentative | G37: 46037 | H37: 46046 | I37: 9 | J37: =TEXT(tblPayments[[#This Row],[Arrival]],"mmm") -> Jan | K37: =MONTH(tblPayments[[#This Row],[Arrival]]) -> 1 | L37: =YEAR(tblPayments[[#This Row],[Arrival]]) -> 2026 | M37: =IF(tblPayments[[#This Row],[Balance]]=0,"Full Payment","Deposit") -> Full Payment | N37: 0 | O37: 45912 | P37: Russia
A38: Resort 1 | B38: 30 days pta | C38: 33970 | D38: 33970 | F38: Fully Paid | G38: 46038 | H38: 46053 | I38: 15 | J38: =TEXT(tblPayments[[#This Row],[Arrival]],"mmm") -> Jan | K38: =MONTH(tblPayments[[#This Row],[Arrival]]) -> 1 | L38: =YEAR(tblPayments[[#This Row],[Arrival]]) -> 2026 | M38: =IF(tblPayments[[#This Row],[Balance]]=0,"Full Payment","Deposit") -> Full Payment | N38: 12213.9 | O38: 45341 | P38: Turkey
A39: Resort 1 | B39: 30 days pta | C39: 83115.1 | E39: 83115.1 | F39: Not paid yet | G39: 46038 | H39: 46044 | I39: 6 | J39: =TEXT(tblPayments[[#This Row],[Arrival]],"mmm") -> Jan | K39: =MONTH(tblPayments[[#This Row],[Arrival]]) -> 1 | L39: =YEAR(tblPayments[[#This Row],[Arrival]]) -> 2026 | M39: =IF(tblPayments[[#This Row],[Balance]]=0,"Full Payment","Deposit") -> Deposit | N39: 52936.44 | O39: 45870 | P39: United States
A40: Resort 1 | B40: 30 days pta | C40: 22025 | E40: 22025 | F40: Not paid yet | G40: 46038 | H40: 46045 | I40: 7 | J40: =TEXT(tblPayments[[#This Row],[Arrival]],"mmm") -> Jan | K40: =MONTH(tblPayments[[#This Row],[Arrival]]) -> 1 | L40: =YEAR(tblPayments[[#This Row],[Arrival]]) -> 2026 | M40: =IF(tblPayments[[#This Row],[Balance]]=0,"Full Payment","Deposit") -> Deposit | N40: 0 | O40: 45989 | P40: Denmark
A41: Resort 1 | B41: 30 days pta | C41: 7420 | E41: 7420 | F41: Not paid yet | G41: 46038 | H41: 46048 | I41: 10 | J41: =TEXT(tblPayments[[#This Row],[Arrival]],"mmm") -> Jan | K41: =MONTH(tblPayments[[#This Row],[Arrival]]) -> 1 | L41: =YEAR(tblPayments[[#This Row],[Arrival]]) -> 2026 | M41: =IF(tblPayments[[#This Row],[Balance]]=0,"Full Payment","Deposit") -> Deposit | N41: 0 | O41: 45947 | P41: Sweden
A42: Resort 1 | B42: 30 days pta | C42: 54114.7 | E42: 54114.7 | F42: Not paid yet | G42: 46039 | H42: 46058 | I42: 19 | J42: =TEXT(tblPayments[[#This Row],[Arrival]],"mmm") -> Jan | K42: =MONTH(tblPayments[[#This Row],[Arrival]]) -> 1 | L42: =YEAR(tblPayments[[#This Row],[Arrival]]) -> 2026 | M42: =IF(tblPayments[[#This Row],[Balance]]=0,"Full Payment","Deposit") -> Deposit | N42: 37079.26 | O42: 45921 | P42: Denmark
A43: Resort 1 | B43: 30 days pta | C43: 150000 | E43: 150000 | F43: Not paid yet | G43: 46039 | H43: 46046 | I43: 7 | J43: =TEXT(tblPayments[[#This Row],[Arrival]],"mmm") -> Jan | K43: =MONTH(tblPayments[[#This Row],[Arrival]]) -> 1 | L43: =YEAR(tblPayments[[#This Row],[Arrival]]) -> 2026 | M43: =IF(tblPayments[[#This Row],[Balance]]=0,"Full Payment","Deposit") -> Deposit | N43: 54116.51 | O43: 45689 | P43: Denmark
A44: Resort 1 | B44: 30 days pta | C44: 66048.64 | E44: 66048.64 | F44: Not paid yet | G44: 46039 | H44: 46067 | I44: 28 | J44: =TEXT(tblPayments[[#This Row],[Arrival]],"mmm") -> Jan | K44: =MONTH(tblPayments[[#This Row],[Arrival]]) -> 1 | L44: =YEAR(tblPayments[[#This Row],[Arrival]]) -> 2026 | M44: =IF(tblPayments[[#This Row],[Balance]]=0,"Full Payment","Deposit") -> Deposit | N44: 30719.92 | O44: 45820 | P44: Denmark
A45: Resort 1 | B45: 30 days pta | C45: 26735.68 | E45: 26735.68 | F45: Not paid yet | G45: 46039 | H45: 46043 | I45: 4 | J45: =TEXT(tblPayments[[#This Row],[Arrival]],"mmm") -> Jan | K45: =MONTH(tblPayments[[#This Row],[Arrival]]) -> 1 | L45: =YEAR(tblPayments[[#This Row],[Arrival]]) -> 2026 | M45: =IF(tblPayments[[#This Row],[Balance]]=0,"Full Payment","Deposit") -> Deposit | N45: 16648.1 | O45: 45902 | P45: India
A46: Resort 1 | B46: 30 days pta | C46: 912 | E46: 912 | F46: Payment on Arrival | G46: 46039 | H46: 46065 | I46: 26 | J46: =TEXT(tblPayments[[#This Row],[Arrival]],"mmm") -> Jan | K46: =MONTH(tblPayments[[#This Row],[Arrival]]) -> 1 | L46: =YEAR(tblPayments[[#This Row],[Arrival]]) -> 2026 | M46: =IF(tblPayments[[#This Row],[Balance]]=0,"Full Payment","Deposit") -> Deposit | N46: 0 | O46: 45829 | P46: UNITED KINGDOM
A47: Resort 1 | B47: 30 days pta | C47: 49652 | E47: 49652 | F47: Not paid yet | G47: 46040 | H47: 46047 | I47: 7 | J47: =TEXT(tblPayments[[#This Row],[Arrival]],"mmm") -> Jan | K47: =MONTH(tblPayments[[#This Row],[Arrival]]) -> 1 | L47: =YEAR(tblPayments[[#This Row],[Arrival]]) -> 2026 | M47: =IF(tblPayments[[#This Row],[Balance]]=0,"Full Payment","Deposit") -> Deposit | N47: 30213.68 | O47: 45996 | P47: Brazil
A48: Resort 1 | B48: 30 days pta | C48: 7284 | D48: 7284 | F48: Fully Paid | G48: 46040 | H48: 46047 | I48: 7 | J48: =TEXT(tblPayments[[#This Row],[Arrival]],"mmm") -> Jan | K48: =MONTH(tblPayments[[#This Row],[Arrival]]) -> 1 | L48: =YEAR(tblPayments[[#This Row],[Arrival]]) -> 2026 | M48: =IF(tblPayments[[#This Row],[Balance]]=0,"Full Payment","Deposit") -> Full Payment | N48: 1314.11 | O48: 45762 | P48: Spain
A49: Resort 1 | B49: 30 days pta | C49: 15482 | E49: 15482 | F49: Credit facility | G49: 46040 | H49: 46043 | I49: 3 | J49: =TEXT(tblPayments[[#This Row],[Arrival]],"mmm") -> Jan | K49: =MONTH(tblPayments[[#This Row],[Arrival]]) -> 1 | L49: =YEAR(tblPayments[[#This Row],[Arrival]]) -> 2026 | M49: =IF(tblPayments[[#This Row],[Balance]]=0,"Full Payment","Deposit") -> Deposit | N49: 9020.97 | O49: 45987 | P49: UNITED KINGDOM
A50: Resort 1 | B50: 30 days pta | C50: 0 | E50: 0 | F50: Comp | G50: 46040 | H50: 46054 | I50: 14 | J50: =TEXT(tblPayments[[#This Row],[Arrival]],"mmm") -> Jan | K50: =MONTH(tblPayments[[#This Row],[Arrival]]) -> 1 | L50: =YEAR(tblPayments[[#This Row],[Arrival]]) -> 2026 | M50: =IF(tblPayments[[#This Row],[Balance]]=0,"Full Payment","Deposit") -> Full Payment | N50: 0 | O50: 45957 | P50: Switzerland
A51: Resort 1 | B51: 30 days pta | C51: 0 | E51: 0 | F51: Comp | G51: 46041 | H51: 46048 | I51: 7 | J51: =TEXT(tblPayments[[#This Row],[Arrival]],"mmm") -> Jan | K51: =MONTH(tblPayments[[#This Row],[Arrival]]) -> 1 | L51: =YEAR(tblPayments[[#This Row],[Arrival]]) -> 2026 | M51: =IF(tblPayments[[#This Row],[Balance]]=0,"Full Payment","Deposit") -> Full Payment | N51: 0 | O51: 45695 | P51: Spain
A52: Resort 1 | B52: 30 days pta | C52: 78926.5 | E52: 78926.5 | F52: Not paid yet | G52: 46041 | H52: 46048 | I52: 7 | J52: =TEXT(tblPayments[[#This Row],[Arrival]],"mmm") -> Jan | K52: =MONTH(tblPayments[[#This Row],[Arrival]]) -> 1 | L52: =YEAR(tblPayments[[#This Row],[Arrival]]) -> 2026 | M52: =IF(tblPayments[[#This Row],[Balance]]=0,"Full Payment","Deposit") -> Deposit | N52: 54617.22 | O52: 45787 | P52: UNITED KINGDOM
A53: Resort 1 | B53: 30 days pta | C53: 70805 | D53: 22397.78 | E53: 48407.22 | F53: Deposit Paid | G53: 46042 | H53: 46052 | I53: 10 | J53: =TEXT(tblPayments[[#This Row],[Arrival]],"mmm") -> Jan | K53: =MONTH(tblPayments[[#This Row],[Arrival]]) -> 1 | L53: =YEAR(tblPayments[[#This Row],[Arrival]]) -> 2026 | M53: =IF(tblPayments[[#This Row],[Balance]]=0,"Full Payment","Deposit") -> Deposit | N53: 38442.5 | O53: 45971 | P53: Poland
A54: Resort 1 | B54: 30 days pta | C54: 25544 | E54: 25544 | F54: Not paid yet | G54: 46042 | H54: 46048 | I54: 6 | J54: =TEXT(tblPayments[[#This Row],[Arrival]],"mmm") -> Jan | K54: =MONTH(tblPayments[[#This Row],[Arrival]]) -> 1 | L54: =YEAR(tblPayments[[#This Row],[Arrival]]) -> 2026 | M54: =IF(tblPayments[[#This Row],[Balance]]=0,"Full Payment","Deposit") -> Deposit | N54: 17109.54 | O54: 45971 | P54: Bulgaria
A55: Resort 1 | B55: 30 days pta | F55: Comp | G55: 46043 | H55: 46047 | I55: 4 | J55: =TEXT(tblPayments[[#This Row],[Arrival]],"mmm") -> Jan | K55: =MONTH(tblPayments[[#This Row],[Arrival]]) -> 1 | L55: =YEAR(tblPayments[[#This Row],[Arrival]]) -> 2026 | M55: =IF(tblPayments[[#This Row],[Balance]]=0,"Full Payment","Deposit") -> Full Payment | O55: 46002
A56: Resort 1 | B56: 30 days pta | C56: 40086 | E56: 40086 | F56: Not paid yet | G56: 46043 | H56: 46050 | I56: 7 | J56: =TEXT(tblPayments[[#This Row],[Arrival]],"mmm") -> Jan | K56: =MONTH(tblPayments[[#This Row],[Arrival]]) -> 1 | L56: =YEAR(tblPayments[[#This Row],[Arrival]]) -> 2026 | M56: =IF(tblPayments[[#This Row],[Balance]]=0,"Full Payment","Deposit") -> Deposit | N56: 19992.21 | O56: 45939 | P56: Germany
A57: Resort 1 | B57: 30 days pta | C57: 0 | E57: 0 | F57: Comp | G57: 46043 | H57: 46050 | I57: 7 | J57: =TEXT(tblPayments[[#This Row],[Arrival]],"mmm") -> Jan | K57: =MONTH(tblPayments[[#This Row],[Arrival]]) -> 1 | L57: =YEAR(tblPayments[[#This Row],[Arrival]]) -> 2026 | M57: =IF(tblPayments[[#This Row],[Balance]]=0,"Full Payment","Deposit") -> Full Payment | N57: 0 | O57: 45847 | P57: Denmark
A58: Resort 1 | B58: 30 days pta | C58: 17682 | E58: 17682 | F58: Not paid yet | G58: 46043 | H58: 46047 | I58: 4 | J58: =TEXT(tblPayments[[#This Row],[Arrival]],"mmm") -> Jan | K58: =MONTH(tblPayments[[#This Row],[Arrival]]) -> 1 | L58: =YEAR(tblPayments[[#This Row],[Arrival]]) -> 2026 | M58: =IF(tblPayments[[#This Row],[Balance]]=0,"Full Payment","Deposit") -> Deposit | N58: 11468.52 | O58: 45896 | P58: United States
A59: Resort 1 | B59: 30 days pta | C59: 22521 | E59: 22521 | F59: Not paid yet | G59: 46043 | H59: 46049 | I59: 6 | J59: =TEXT(tblPayments[[#This Row],[Arrival]],"mmm") -> Jan | K59: =MONTH(tblPayments[[#This Row],[Arrival]]) -> 1 | L59: =YEAR(tblPayments[[#This Row],[Arrival]]) -> 2026 | M59: =IF(tblPayments[[#This Row],[Balance]]=0,"Full Payment","Deposit") -> Deposit | N59: 13487.16 | O59: 46000 | P59: Russia
A60: Resort 1 | B60: 30 days pta | C60: 34520 | E60: 34520 | F60: Not paid yet | G60: 46044 | H60: 46049 | I60: 5 | J60: =TEXT(tblPayments[[#This Row],[Arrival]],"mmm") -> Jan | K60: =MONTH(tblPayments[[#This Row],[Arrival]]) -> 1 | L60: =YEAR(tblPayments[[#This Row],[Arrival]]) -> 2026 | M60: =IF(tblPayments[[#This Row],[Balance]]=0,"Full Payment","Deposit") -> Deposit | N60: 15066.05 | O60: 45687 | P60: UNITED KINGDOM
A61: Resort 1 | B61: 30 days pta | C61: 18872.48 | D61: 16272.48 | E61: 2600 | F61: Deposit Paid | G61: 46044 | H61: 46047 | I61: 3 | J61: =TEXT(tblPayments[[#This Row],[Arrival]],"mmm") -> Jan | K61: =MONTH(tblPayments[[#This Row],[Arrival]]) -> 1 | L61: =YEAR(tblPayments[[#This Row],[Arrival]]) -> 2026 | M61: =IF(tblPayments[[#This Row],[Balance]]=0,"Full Payment","Deposit") -> Deposit | N61: 12065.37 | O61: 45955 | P61: Hong Kong SAR of China
A62: Resort 1 | B62: 30 days pta | C62: 72686 | E62: 72686 | F62: Not paid yet | G62: 46045 | H62: 46052 | I62: 7 | J62: =TEXT(tblPayments[[#This Row],[Arrival]],"mmm") -> Jan | K62: =MONTH(tblPayments[[#This Row],[Arrival]]) -> 1 | L62: =YEAR(tblPayments[[#This Row],[Arrival]]) -> 2026 | M62: =IF(tblPayments[[#This Row],[Balance]]=0,"Full Payment","Deposit") -> Deposit | N62: 40194.28 | O62: 45974 | P62: Turkey
A63: Resort 1 | B63: 30 days pta | C63: 12816 | E63: 12816 | F63: Not paid yet | G63: 46045 | H63: 46047 | I63: 2 | J63: =TEXT(tblPayments[[#This Row],[Arrival]],"mmm") -> Jan | K63: =MONTH(tblPayments[[#This Row],[Arrival]]) -> 1 | L63: =YEAR(tblPayments[[#This Row],[Arrival]]) -> 2026 | M63: =IF(tblPayments[[#This Row],[Balance]]=0,"Full Payment","Deposit") -> Deposit | N63: 4479.41 | O63: 45989 | P63: China
A64: Resort 1 | B64: 30 days pta | C64: 18947.98 | D64: 18947.98 | F64: Fully Paid | G64: 46046 | H64: 46050 | I64: 4 | J64: =TEXT(tblPayments[[#This Row],[Arrival]],"mmm") -> Jan | K64: =MONTH(tblPayments[[#This Row],[Arrival]]) -> 1 | L64: =YEAR(tblPayments[[#This Row],[Arrival]]) -> 2026 | M64: =IF(tblPayments[[#This Row],[Balance]]=0,"Full Payment","Deposit") -> Full Payment | N64: 11471.28 | O64: 45785 | P64: France
A65: Resort 1 | B65: 30 days pta | F65: Comp | G65: 46046 | H65: 46052 | I65: 6 | J65: =TEXT(tblPayments[[#This Row],[Arrival]],"mmm") -> Jan | K65: =MONTH(tblPayments[[#This Row],[Arrival]]) -> 1 | L65: =YEAR(tblPayments[[#This Row],[Arrival]]) -> 2026 | M65: =IF(tblPayments[[#This Row],[Balance]]=0,"Full Payment","Deposit") -> Full Payment | N65: 0 | O65: 45995 | P65: India
A66: Resort 1 | B66: 30 days pta | C66: 19224 | E66: 19224 | F66: Not paid yet | G66: 46047 | H66: 46050 | I66: 3 | J66: =TEXT(tblPayments[[#This Row],[Arrival]],"mmm") -> Jan | K66: =MONTH(tblPayments[[#This Row],[Arrival]]) -> 1 | L66: =YEAR(tblPayments[[#This Row],[Arrival]]) -> 2026 | M66: =IF(tblPayments[[#This Row],[Balance]]=0,"Full Payment","Deposit") -> Deposit | N66: 12546.63 | O66: 45989 | P66: China
A67: Resort 1 | B67: 30 days pta | C67: 36837.98 | D67: 18419.2 | E67: 18419.2 | F67: Deposit Paid | G67: 46048 | H67: 46055 | I67: 7 | J67: =TEXT(tblPayments[[#This Row],[Arrival]],"mmm") -> Jan | K67: =MONTH(tblPayments[[#This Row],[Arrival]]) -> 1 | L67: =YEAR(tblPayments[[#This Row],[Arrival]]) -> 2026 | M67: =IF(tblPayments[[#This Row],[Balance]]=0,"Full Payment","Deposit") -> Deposit | N67: 22634.29 | O67: 45911 | P67: UNITED KINGDOM
A68: Resort 1 | B68: 30 days pta | C68: 380 | E68: 380 | F68: Not paid yet | G68: 46048 | H68: 46050 | I68: 2 | J68: =TEXT(tblPayments[[#This Row],[Arrival]],"mmm") -> Jan | K68: =MONTH(tblPayments[[#This Row],[Arrival]]) -> 1 | L68: =YEAR(tblPayments[[#This Row],[Arrival]]) -> 2026 | M68: =IF(tblPayments[[#This Row],[Balance]]=0,"Full Payment","Deposit") -> Deposit | N68: 0 | O68: 45939 | P68: Germany
A69: Resort 1 | B69: 30 days pta | C69: 73887.5 | D69: 73887.5 | F69: Fully Paid | G69: 46048 | H69: 46055 | I69: 7 | J69: =TEXT(tblPayments[[#This Row],[Arrival]],"mmm") -> Jan | K69: =MONTH(tblPayments[[#This Row],[Arrival]]) -> 1 | L69: =YEAR(tblPayments[[#This Row],[Arrival]]) -> 2026 | M69: =IF(tblPayments[[#This Row],[Balance]]=0,"Full Payment","Deposit") -> Full Payment | N69: 23605.54 | O69: 45879 | P69: UNITED KINGDOM
A70: Resort 1 | B70: 30 days pta | C70: 0 | E70: 0 | F70: Comp | G70: 46048 | H70: 46059 | I70: 11 | J70: =TEXT(tblPayments[[#This Row],[Arrival]],"mmm") -> Jan | K70: =MONTH(tblPayments[[#This Row],[Arrival]]) -> 1 | L70: =YEAR(tblPayments[[#This Row],[Arrival]]) -> 2026 | M70: =IF(tblPayments[[#This Row],[Balance]]=0,"Full Payment","Deposit") -> Full Payment | N70: 0 | O70: 45937 | P70: Sweden
A71: Resort 1 | B71: 30 days pta | C71: 397 | E71: 397 | F71: Not paid yet | G71: 46048 | H71: 46051 | I71: 3 | J71: =TEXT(tblPayments[[#This Row],[Arrival]],"mmm") -> Jan | K71: =MONTH(tblPayments[[#This Row],[Arrival]]) -> 1 | L71: =YEAR(tblPayments[[#This Row],[Arrival]]) -> 2026 | M71: =IF(tblPayments[[#This Row],[Balance]]=0,"Full Payment","Deposit") -> Deposit | N71: 0 | O71: 45981 | P71: China
A72: Resort 1 | B72: 30 days pta | C72: 1200 | E72: 1200 | F72: Not paid yet | G72: 46048 | H72: 46051 | I72: 3 | J72: =TEXT(tblPayments[[#This Row],[Arrival]],"mmm") -> Jan | K72: =MONTH(tblPayments[[#This Row],[Arrival]]) -> 1 | L72: =YEAR(tblPayments[[#This Row],[Arrival]]) -> 2026 | M72: =IF(tblPayments[[#This Row],[Balance]]=0,"Full Payment","Deposit") -> Deposit | N72: 386.91 | O72: 45915 | P72: China
A73: Resort 1 | B73: 30 days pta | C73: 13797 | E73: 13797 | F73: Not paid yet | G73: 46049 | H73: 46051 | I73: 2 | J73: =TEXT(tblPayments[[#This Row],[Arrival]],"mmm") -> Jan | K73: =MONTH(tblPayments[[#This Row],[Arrival]]) -> 1 | L73: =YEAR(tblPayments[[#This Row],[Arrival]]) -> 2026 | M73: =IF(tblPayments[[#This Row],[Balance]]=0,"Full Payment","Deposit") -> Deposit | N73: 0 | O73: 45689 | P73: UNITED KINGDOM
A74: Resort 1 | B74: 30 days pta | C74: 0 | E74: 0 | F74: Comp | G74: 46049 | H74: 46073 | I74: 24 | J74: =TEXT(tblPayments[[#This Row],[Arrival]],"mmm") -> Jan | K74: =MONTH(tblPayments[[#This Row],[Arrival]]) -> 1 | L74: =YEAR(tblPayments[[#This Row],[Arrival]]) -> 2026 | M74: =IF(tblPayments[[#This Row],[Balance]]=0,"Full Payment","Deposit") -> Full Payment | N74: 0 | O74: 45918 | P74: Russia
A75: Resort 1 | B75: 30 days pta | C75: 24252.37 | E75: 24252.37 | F75: Not paid yet | G75: 46049 | H75: 46052 | I75: 3 | J75: =TEXT(tblPayments[[#This Row],[Arrival]],"mmm") -> Jan | K75: =MONTH(tblPayments[[#This Row],[Arrival]]) -> 1 | L75: =YEAR(tblPayments[[#This Row],[Arrival]]) -> 2026 | M75: =IF(tblPayments[[#This Row],[Balance]]=0,"Full Payment","Deposit") -> Deposit | N75: 0 | O75: 45966 | P75: UNITED KINGDOM
A76: Resort 1 | B76: 30 days pta | C76: 147338 | D76: 36834.5 | E76: 110503.5 | F76: Deposit Paid | G76: 46050 | H76: 46057 | I76: 7 | J76: =TEXT(tblPayments[[#This Row],[Arrival]],"mmm") -> Jan | K76: =MONTH(tblPayments[[#This Row],[Arrival]]) -> 1 | L76: =YEAR(tblPayments[[#This Row],[Arrival]]) -> 2026 | M76: =IF(tblPayments[[#This Row],[Balance]]=0,"Full Payment","Deposit") -> Deposit | N76: 48317.29 | O76: 45967 | P76: Sweden
A77: Resort 1 | B77: 30 days pta | C77: 0 | E77: 0 | F77: Comp | G77: 46050 | H77: 46057 | I77: 7 | J77: =TEXT(tblPayments[[#This Row],[Arrival]],"mmm") -> Jan | K77: =MONTH(tblPayments[[#This Row],[Arrival]]) -> 1 | L77: =YEAR(tblPayments[[#This Row],[Arrival]]) -> 2026 | M77: =IF(tblPayments[[#This Row],[Balance]]=0,"Full Payment","Deposit") -> Full Payment | N77: 0 | O77: 45935 | P77: UNITED KINGDOM
A78: Resort 1 | B78: 30 days pta | C78: 19395.96 | E78: 19395.96 | F78: Not paid yet | G78: 46051 | H78: 46057 | I78: 6 | J78: =TEXT(tblPayments[[#This Row],[Arrival]],"mmm") -> Jan | K78: =MONTH(tblPayments[[#This Row],[Arrival]]) -> 1 | L78: =YEAR(tblPayments[[#This Row],[Arrival]]) -> 2026 | M78: =IF(tblPayments[[#This Row],[Balance]]=0,"Full Payment","Deposit") -> Deposit | N78: 12580.86 | O78: 46000 | P78: UNITED KINGDOM
A79: Resort 1 | B79: 30 days pta | C79: 27320 | E79: 27320 | F79: Not paid yet | G79: 46052 | H79: 46057 | I79: 5 | J79: =TEXT(tblPayments[[#This Row],[Arrival]],"mmm") -> Jan | K79: =MONTH(tblPayments[[#This Row],[Arrival]]) -> 1 | L79: =YEAR(tblPayments[[#This Row],[Arrival]]) -> 2026 | M79: =IF(tblPayments[[#This Row],[Balance]]=0,"Full Payment","Deposit") -> Deposit | N79: 17361.1 | O79: 45965 | P79: Germany
A80: Resort 1 | B80: 30 days pta | C80: 325 | E80: 325 | F80: Not paid yet | G80: 46052 | H80: 46054 | I80: 2 | J80: =TEXT(tblPayments[[#This Row],[Arrival]],"mmm") -> Jan | K80: =MONTH(tblPayments[[#This Row],[Arrival]]) -> 1 | L80: =YEAR(tblPayments[[#This Row],[Arrival]]) -> 2026 | M80: =IF(tblPayments[[#This Row],[Balance]]=0,"Full Payment","Deposit") -> Deposit | N80: -1144.68 | O80: 45981 | P80: UNITED KINGDOM
A81: Resort 1 | B81: 30 days pta | C81: 8311.2 | E81: 8311.2 | F81: Against VCC | G81: 46052 | H81: 46053 | I81: 1 | J81: =TEXT(tblPayments[[#This Row],[Arrival]],"mmm") -> Jan | K81: =MONTH(tblPayments[[#This Row],[Arrival]]) -> 1 | L81: =YEAR(tblPayments[[#This Row],[Arrival]]) -> 2026 | M81: =IF(tblPayments[[#This Row],[Balance]]=0,"Full Payment","Deposit") -> Deposit | N81: 4197.73 | O81: 45986 | P81: Korea (South)
A82: Resort 1 | B82: 30 days pta | C82: 13600 | E82: 13600 | F82: Not paid yet | G82: 46053 | H82: 46067 | I82: 14 | J82: =TEXT(tblPayments[[#This Row],[Arrival]],"mmm") -> Jan | K82: =MONTH(tblPayments[[#This Row],[Arrival]]) -> 1 | L82: =YEAR(tblPayments[[#This Row],[Arrival]]) -> 2026 | M82: =IF(tblPayments[[#This Row],[Balance]]=0,"Full Payment","Deposit") -> Deposit | N82: 0 | O82: 45748 | P82: Denmark
A83: Resort 1 | B83: 30 days pta | C83: 35074 | D83: 35074 | F83: Fully Paid | G83: 46053 | H83: 46062 | I83: 9 | J83: =TEXT(tblPayments[[#This Row],[Arrival]],"mmm") -> Jan | K83: =MONTH(tblPayments[[#This Row],[Arrival]]) -> 1 | L83: =YEAR(tblPayments[[#This Row],[Arrival]]) -> 2026 | M83: =IF(tblPayments[[#This Row],[Balance]]=0,"Full Payment","Deposit") -> Full Payment | N83: 19842.66 | O83: 45849 | P83: Russia
A84: Resort 1 | B84: 30 days pta | C84: 60160 | E84: 60160 | F84: Not paid yet | G84: 46053 | H84: 46062 | I84: 9 | J84: =TEXT(tblPayments[[#This Row],[Arrival]],"mmm") -> Jan | K84: =MONTH(tblPayments[[#This Row],[Arrival]]) -> 1 | L84: =YEAR(tblPayments[[#This Row],[Arrival]]) -> 2026 | M84: =IF(tblPayments[[#This Row],[Balance]]=0,"Full Payment","Deposit") -> Deposit | N84: 34232.67 | O84: 45776 | P84: Denmark
A85: Resort 1 | B85: 30 days pta | C85: 35340 | E85: 35340 | F85: Not paid yet | G85: 46053 | H85: 46062 | I85: 9 | J85: =TEXT(tblPayments[[#This Row],[Arrival]],"mmm") -> Jan | K85: =MONTH(tblPayments[[#This Row],[Arrival]]) -> 1 | L85: =YEAR(tblPayments[[#This Row],[Arrival]]) -> 2026 | M85: =IF(tblPayments[[#This Row],[Balance]]=0,"Full Payment","Deposit") -> Deposit | N85: 16787.79 | O85: 45776 | P85: Denmark
A86: Resort 1 | B86: 30 days pta | C86: 35340 | E86: 35340 | F86: Not paid yet | G86: 46053 | H86: 46062 | I86: 9 | J86: =TEXT(tblPayments[[#This Row],[Arrival]],"mmm") -> Jan | K86: =MONTH(tblPayments[[#This Row],[Arrival]]) -> 1 | L86: =YEAR(tblPayments[[#This Row],[Arrival]]) -> 2026 | M86: =IF(tblPayments[[#This Row],[Balance]]=0,"Full Payment","Deposit") -> Deposit | N86: 16787.79 | O86: 45776 | P86: Denmark
A87: Resort 1 | B87: 30 days pta | C87: 78903.44 | E87: 78903.44 | F87: Not paid yet | G87: 46053 | H87: 46067 | I87: 14 | J87: =TEXT(tblPayments[[#This Row],[Arrival]],"mmm") -> Jan | K87: =MONTH(tblPayments[[#This Row],[Arrival]]) -> 1 | L87: =YEAR(tblPayments[[#This Row],[Arrival]]) -> 2026 | M87: =IF(tblPayments[[#This Row],[Balance]]=0,"Full Payment","Deposit") -> Deposit | N87: 54363.82 | O87: 45735 | P87: Denmark
A88: Resort 1 | B88: 30 days pta | C88: 33144 | D88: 17903.79 | E88: 15240.21 | F88: Deposit Paid | G88: 46053 | H88: 46059 | I88: 6 | J88: =TEXT(tblPayments[[#This Row],[Arrival]],"mmm") -> Jan | K88: =MONTH(tblPayments[[#This Row],[Arrival]]) -> 1 | L88: =YEAR(tblPayments[[#This Row],[Arrival]]) -> 2026 | M88: =IF(tblPayments[[#This Row],[Balance]]=0,"Full Payment","Deposit") -> Deposit | N88: 19169.76 | O88: 45723 | P88: France
A89: Resort 1 | B89: 30 days pta | C89: 0 | E89: 0 | F89: Comp | G89: 46054 | H89: 46061 | I89: 7 | J89: =TEXT(tblPayments[[#This Row],[Arrival]],"mmm") -> Feb | K89: =MONTH(tblPayments[[#This Row],[Arrival]]) -> 2 | L89: =YEAR(tblPayments[[#This Row],[Arrival]]) -> 2026 | M89: =IF(tblPayments[[#This Row],[Balance]]=0,"Full Payment","Deposit") -> Full Payment | N89: 0 | O89: 45821 | P89: Russia
A90: Resort 1 | B90: 30 days pta | C90: 26072 | D90: 6518 | E90: 19554 | F90: Deposit Paid | G90: 46054 | H90: 46060 | I90: 6 | J90: =TEXT(tblPayments[[#This Row],[Arrival]],"mmm") -> Feb | K90: =MONTH(tblPayments[[#This Row],[Arrival]]) -> 2 | L90: =YEAR(tblPayments[[#This Row],[Arrival]]) -> 2026 | M90: =IF(tblPayments[[#This Row],[Balance]]=0,"Full Payment","Deposit") -> Deposit | N90: 17206.98 | O90: 45984 | P90: Russia
A91: Resort 1 | B91: 30 days pta | C91: 15118 | E91: 15118 | F91: Not paid yet | G91: 46054 | H91: 46061 | I91: 7 | J91: =TEXT(tblPayments[[#This Row],[Arrival]],"mmm") -> Feb | K91: =MONTH(tblPayments[[#This Row],[Arrival]]) -> 2 | L91: =YEAR(tblPayments[[#This Row],[Arrival]]) -> 2026 | M91: =IF(tblPayments[[#This Row],[Balance]]=0,"Full Payment","Deposit") -> Deposit | N91: 8616.93 | O91: 45901 | P91: UNITED KINGDOM
A92: Resort 1 | B92: 30 days pta | C92: 38096 | E92: 38096 | F92: Not paid yet | G92: 46055 | H92: 46064 | I92: 9 | J92: =TEXT(tblPayments[[#This Row],[Arrival]],"mmm") -> Feb | K92: =MONTH(tblPayments[[#This Row],[Arrival]]) -> 2 | L92: =YEAR(tblPayments[[#This Row],[Arrival]]) -> 2026 | M92: =IF(tblPayments[[#This Row],[Balance]]=0,"Full Payment","Deposit") -> Deposit | N92: 26503.47 | O92: 45926 | P92: UNITED KINGDOM
A93: Resort 1 | B93: 30 days pta | C93: 73887.5 | D93: 73887.5 | F93: Fully Paid | G93: 46055 | H93: 46058 | I93: 3 | J93: =TEXT(tblPayments[[#This Row],[Arrival]],"mmm") -> Feb | K93: =MONTH(tblPayments[[#This Row],[Arrival]]) -> 2 | L93: =YEAR(tblPayments[[#This Row],[Arrival]]) -> 2026 | M93: =IF(tblPayments[[#This Row],[Balance]]=0,"Full Payment","Deposit") -> Full Payment | N93: 0 | O93: 45879 | P93: UNITED KINGDOM
A94: Resort 1 | B94: 30 days pta | C94: 19688.2 | D94: 4922.05 | E94: 14766.15 | F94: Deposit Paid | G94: 46055 | H94: 46059 | I94: 4 | J94: =TEXT(tblPayments[[#This Row],[Arrival]],"mmm") -> Feb | K94: =MONTH(tblPayments[[#This Row],[Arrival]]) -> 2 | L94: =YEAR(tblPayments[[#This Row],[Arrival]]) -> 2026 | M94: =IF(tblPayments[[#This Row],[Balance]]=0,"Full Payment","Deposit") -> Deposit | N94: 13599.04 | O94: 45955 | P94: UNITED KINGDOM
A95: Resort 1 | B95: 30 days pta | C95: 0 | E95: 0 | F95: Comp | G95: 46055 | H95: 46062 | I95: 7 | J95: =TEXT(tblPayments[[#This Row],[Arrival]],"mmm") -> Feb | K95: =MONTH(tblPayments[[#This Row],[Arrival]]) -> 2 | L95: =YEAR(tblPayments[[#This Row],[Arrival]]) -> 2026 | M95: =IF(tblPayments[[#This Row],[Balance]]=0,"Full Payment","Deposit") -> Full Payment | N95: 0 | O95: 45987 | P95: UNITED KINGDOM
A96: Resort 1 | B96: 30 days pta | C96: 29644 | E96: 29644 | F96: Not paid yet | G96: 46056 | H96: 46062 | I96: 6 | J96: =TEXT(tblPayments[[#This Row],[Arrival]],"mmm") -> Feb | K96: =MONTH(tblPayments[[#This Row],[Arrival]]) -> 2 | L96: =YEAR(tblPayments[[#This Row],[Arrival]]) -> 2026 | M96: =IF(tblPayments[[#This Row],[Balance]]=0,"Full Payment","Deposit") -> Deposit | N96: 18974.34 | O96: 45755 | P96: UNITED KINGDOM
A97: Resort 1 | B97: 30 days pta | C97: 900 | E97: 900 | F97: Not paid yet | G97: 46057 | H97: 46059 | I97: 2 | J97: =TEXT(tblPayments[[#This Row],[Arrival]],"mmm") -> Feb | K97: =MONTH(tblPayments[[#This Row],[Arrival]]) -> 2 | L97: =YEAR(tblPayments[[#This Row],[Arrival]]) -> 2026 | M97: =IF(tblPayments[[#This Row],[Balance]]=0,"Full Payment","Deposit") -> Deposit | N97: 0 | O97: 45869 | P97: Russia
A98: Resort 1 | B98: 30 days pta | C98: 85090 | D98: 85090 | F98: Fully Paid | G98: 46058 | H98: 46073 | I98: 15 | J98: =TEXT(tblPayments[[#This Row],[Arrival]],"mmm") -> Feb | K98: =MONTH(tblPayments[[#This Row],[Arrival]]) -> 2 | L98: =YEAR(tblPayments[[#This Row],[Arrival]]) -> 2026 | M98: =IF(tblPayments[[#This Row],[Balance]]=0,"Full Payment","Deposit") -> Full Payment | N98: 51024.45 | O98: 45742 | P98: Netherlands
A99: Resort 1 | B99: 30 days pta | C99: 37015 | E99: 37015 | F99: Not paid yet | G99: 46058 | H99: 46068 | I99: 10 | J99: =TEXT(tblPayments[[#This Row],[Arrival]],"mmm") -> Feb | K99: =MONTH(tblPayments[[#This Row],[Arrival]]) -> 2 | L99: =YEAR(tblPayments[[#This Row],[Arrival]]) -> 2026 | M99: =IF(tblPayments[[#This Row],[Balance]]=0,"Full Payment","Deposit") -> Deposit | N99: 13255.6 | O99: 45840 | P99: Denmark
A100: Resort 1 | B100: 30 days pta | C100: 1680 | E100: 1680 | F100: Not paid yet | G100: 46058 | H100: 46082 | I100: 24 | J100: =TEXT(tblPayments[[#This Row],[Arrival]],"mmm") -> Feb | K100: =MONTH(tblPayments[[#This Row],[Arrival]]) -> 2 | L100: =YEAR(tblPayments[[#This Row],[Arrival]]) -> 2026 | M100: =IF(tblPayments[[#This Row],[Balance]]=0,"Full Payment","Deposit") -> Deposit | N100: 0 | O100: 45804 | P100: Germany
...

Sheet Resort 1
A1: Resort | B1: Due Date | C1: Invoice Amount | D1: Payment Received | E1: Balance | F1: Payment Status | G1: Arrival | H1: Departure | I1: No of nights | J1: Room Revenue | K1: Date Entered | L1: Country
A2: Resort 1 | B2: 90 days pta | C2: 199999.97 | D2: 199999.97 | F2: Fully Paid | G2: 46023 | H2: 46030 | I2: 7 | J2: 137553.57 | K2: 45933 | L2: Russia
A3: Resort 1 | B3: 90 days pta | C3: 209974.09 | D3: 209974.09 | F3: Fully Paid | G3: 46023 | H3: 46030 | I3: 7 | J3: 149217.09 | K3: 45861 | L3: UNITED KINGDOM
A4: Resort 1 | B4: 90 days pta | C4: 136440 | D4: 136440 | F4: Fully Paid | G4: 46024 | H4: 46034 | I4: 10 | J4: 95268.04 | K4: 45895 | L4: Russia
A5: Resort 1 | B5: 90 days pta | C5: 131512 | D5: 131512 | F5: Fully Paid | G5: 46024 | H5: 46033 | I5: 9 | J5: 90370.98 | K5: 45973 | L5: Russia
A6: Resort 1 | B6: 90 days pta | C6: 65778 | D6: 65778 | F6: Fully Paid | G6: 46025 | H6: 46032 | I6: 7 | J6: 36985.27 | K6: 45736 | L6: UNITED KINGDOM
A7: Resort 1 | B7: 90 days pta | C7: 116300 | D7: 116300 | F7: Fully Paid | G7: 46025 | H7: 46034 | I7: 9 | J7: 84335.67 | K7: 45901 | L7: Russia
A8: Resort 1 | B8: 90 days pta | C8: 78492.39 | D8: 78824.54 | F8: Fully Paid | G8: 46025 | H8: 46032 | I8: 7 | J8: 57379.84 | K8: 45833 | L8: Russia
A9: Resort 1 | B9: 90 days pta | C9: 20030.88 | D9: 20030.88 | F9: Fully Paid | G9: 46026 | H9: 46030 | I9: 4 | J9: 11604.76 | K9: 45912 | L9: India
A10: Resort 1 | B10: 90 days pta | C10: 85106 | D10: 85106 | F10: Fully Paid | G10: 46026 | H10: 46031 | I10: 5 | J10: 59803.1 | K10: 45933 | L10: Greece
A11: Resort 1 | B11: 90 days pta | C11: 0 | D11: 0 | F11: Comp | G11: 46026 | H11: 46028 | I11: 2 | J11: 0 | K11: 45973 | L11: Thailand
A12: Resort 1 | B12: 90 days pta | C12: 0 | D12: 0 | F12: Tentative | G12: 46026 | H12: 46033 | I12: 7 | J12: 22696.94 | K12: 46001 | L12: Unknown
A13: Resort 1 | B13: 90 days pta | C13: 0 | D13: 0 | F13: Tentative | G13: 46026 | H13: 46033 | I13: 7 | J13: 22696.94 | K13: 46001 | L13: Unknown
A14: Resort 1 | B14: 90 days pta | C14: 18682.88 | D14: 18682.88 | F14: Fully Paid | G14: 46026 | H14: 46030 | I14: 4 | J14: 11766.56 | K14: 45837 | L14: Unknown
A15: Resort 1 | B15: 90 days pta | C15: 63049.9 | D15: 2600 | E15: 60449.9 | F15: Against VCC | G15: 46027 | H15: 46036 | I15: 9 | J15: 45073.17 | K15: 45938 | L15: France
A16: Resort 1 | B16: 90 days pta | C16: 43204 | D16: 43204 | F16: Fully Paid | G16: 46027 | H16: 46033 | I16: 6 | J16: 30396.3 | K16: 45975 | L16: Germany
A17: Resort 1 | B17: 90 days pta | C17: 30367.55 | D17: 30367.55 | F17: Fully Paid | G17: 46027 | H17: 46030 | I17: 3 | J17: 21402.3 | K17: 45961 | L17: Japan
A18: Resort 1 | B18: 90 days pta | C18: 56372.1 | D18: 56372.1 | F18: Deposit Paid | G18: 46028 | H18: 46035 | I18: 7 | J18: 38085.53 | K18: 45976 | L18: Russia
A19: Resort 1 | B19: 90 days pta | C19: 0 | D19: 0 | F19: Comp | G19: 46028 | H19: 46033 | I19: 5 | J19: 0 | K19: 45975 | L19: Russia
A20: Resort 1 | B20: 90 days pta | F20: Comp | G20: 46029 | H20: 46036 | I20: 7 | J20: 10040.38
A21: Resort 1 | B21: 90 days pta | C21: 19000 | D21: 11017.78 | E21: 7982.22 | F21: Deposit Paid | G21: 46029 | H21: 46045 | I21: 16 | J21: 0 | K21: 45743 | L21: Switzerland
A22: Resort 1 | B22: 90 days pta | C22: 52368.8 | E22: 52368.8 | F22: Not paid yet | G22: 46030 | H22: 46037 | I22: 7 | J22: 37832.76 | K22: 45995 | L22: Kuwait
A23: Resort 1 | B23: 90 days pta | F23: Tentative | G23: 46030 | H23: 46046 | I23: 16 | J23: 10622.68 | K23: 45932 | L23: Switzerland
A24: Resort 1 | B24: 90 days pta | C24: 0 | D24: 0 | F24: Comp | G24: 46031 | H24: 46038 | I24: 7 | J24: 0 | K24: 45674 | L24: UNITED KINGDOM
A25: Resort 1 | B25: 90 days pta | C25: 67954.74 | D25: 67954.74 | F25: Fully Paid | G25: 46031 | H25: 46039 | I25: 8 | J25: 49406.1 | K25: 45980 | L25: Argentina
A26: Resort 1 | B26: 90 days pta | C26: 157003.12 | D26: 157003.12 | F26: Fully Paid | G26: 46032 | H26: 46040 | I26: 8 | J26: 107244.08 | K26: 45792 | L26: Finland
A27: Resort 1 | B27: 30 days pta | C27: 33897 | D27: 33897 | F27: Fully Paid | G27: 46034 | H27: 46040 | I27: 6 | J27: 20535.72 | K27: 45966 | L27: Russia
A28: Resort 1 | B28: 30 days pta | C28: 41700 | D28: 41700 | F28: Fully Paid | G28: 46034 | H28: 46043 | I28: 9 | J28: 10003.08 | K28: 45911 | L28: Sweden
A29: Resort 1 | B29: 30 days pta | C29: 58243.22 | E29: 58243.22 | F29: Not paid yet | G29: 46034 | H29: 46048 | I29: 14 | J29: 34161.12 | K29: 45777 | L29: Sweden
A30: Resort 1 | B30: 30 days pta | F30: Tentative | G30: 46034 | H30: 46038 | I30: 4 | K30: 46002
A31: Resort 1 | B31: 30 days pta | C31: 29085 | E31: 29085 | F31: Not paid yet | G31: 46035 | H31: 46040 | I31: 5 | J31: 19570.7 | K31: 45998 | L31: Switzerland
A32: Resort 1 | B32: 30 days pta | C32: 43861.8 | D32: 18861.8 | E32: 25000 | F32: Deposit Paid | G32: 46035 | H32: 46041 | I32: 6 | J32: 32644.74 | K32: 45976 | L32: Russia
A33: Resort 1 | B33: 30 days pta | C33: 127800.88 | D33: 50000 | E33: 77800.88 | F33: Deposit Paid | G33: 46035 | H33: 46049 | I33: 14 | J33: 88943.12 | K33: 45917 | L33: Russia
A34: Resort 1 | B34: 30 days pta | C34: 103950 | D34: 103950 | F34: Fully Paid | G34: 46035 | H34: 46045 | I34: 10 | J34: 0 | K34: 45555 | L34: United States
A35: Resort 1 | B35: 30 days pta | C35: 91560 | E35: 91560 | F35: Not paid yet | G35: 46036 | H35: 46066 | I35: 30 | J35: 47179.5 | K35: 45776 | L35: Denmark
A36: Resort 1 | B36: 30 days pta | C36: 136400.34 | E36: 136400.34 | F36: Not paid yet | G36: 46036 | H36: 46054 | I36: 18 | J36: 87639.12 | K36: 45861 | L36: Argentina
A37: Resort 1 | B37: 30 days pta | F37: Tentative | G37: 46037 | H37: 46046 | I37: 9 | J37: 0 | K37: 45912 | L37: Russia
A38: Resort 1 | B38: 30 days pta | C38: 33970 | D38: 33970 | F38: Fully Paid | G38: 46038 | H38: 46053 | I38: 15 | J38: 12213.9 | K38: 45341 | L38: Turkey
A39: Resort 1 | B39: 30 days pta | C39: 83115.1 | E39: 83115.1 | F39: Not paid yet | G39: 46038 | H39: 46044 | I39: 6 | J39: 52936.44 | K39: 45870 | L39: United States
A40: Resort 1 | B40: 30 days pta | C40: 22025 | E40: 22025 | F40: Not paid yet | G40: 46038 | H40: 46045 | I40: 7 | J40: 0 | K40: 45989 | L40: Denmark
A41: Resort 1 | B41: 30 days pta | C41: 7420 | E41: 7420 | F41: Not paid yet | G41: 46038 | H41: 46048 | I41: 10 | J41: 0 | K41: 45947 | L41: Sweden
A42: Resort 1 | B42: 30 days pta | C42: 54114.7 | E42: 54114.7 | F42: Not paid yet | G42: 46039 | H42: 46058 | I42: 19 | J42: 37079.26 | K42: 45921 | L42: Denmark
A43: Resort 1 | B43: 30 days pta | C43: 150000 | E43: 150000 | F43: Not paid yet | G43: 46039 | H43: 46046 | I43: 7 | J43: 54116.51 | K43: 45689 | L43: Denmark
A44: Resort 1 | B44: 30 days pta | C44: 66048.64 | E44: 66048.64 | F44: Not paid yet | G44: 46039 | H44: 46067 | I44: 28 | J44: 30719.92 | K44: 45820 | L44: Denmark
A45: Resort 1 | B45: 30 days pta | C45: 26735.68 | E45: 26735.68 | F45: Not paid yet | G45: 46039 | H45: 46043 | I45: 4 | J45: 16648.1 | K45: 45902 | L45: India
A46: Resort 1 | B46: 30 days pta | C46: 912 | E46: 912 | F46: Payment on Arrival | G46: 46039 | H46: 46065 | I46: 26 | J46: 0 | K46: 45829 | L46: UNITED KINGDOM
A47: Resort 1 | B47: 30 days pta | C47: 49652 | E47: 49652 | F47: Not paid yet | G47: 46040 | H47: 46047 | I47: 7 | J47: 30213.68 | K47: 45996 | L47: Brazil
A48: Resort 1 | B48: 30 days pta | C48: 7284 | D48: 7284 | F48: Fully Paid | G48: 46040 | H48: 46047 | I48: 7 | J48: 1314.11 | K48: 45762 | L48: Spain
A49: Resort 1 | B49: 30 days pta | C49: 15482 | E49: 15482 | F49: Credit facility | G49: 46040 | H49: 46043 | I49: 3 | J49: 9020.97 | K49: 45987 | L49: UNITED KINGDOM
A50: Resort 1 | B50: 30 days pta | C50: 0 | E50: 0 | F50: Comp | G50: 46040 | H50: 46054 | I50: 14 | J50: 0 | K50: 45957 | L50: Switzerland
A51: Resort 1 | B51: 30 days pta | C51: 0 | E51: 0 | F51: Comp | G51: 46041 | H51: 46048 | I51: 7 | J51: 0 | K51: 45695 | L51: Spain
A52: Resort 1 | B52: 30 days pta | C52: 78926.5 | E52: 78926.5 | F52: Not paid yet | G52: 46041 | H52: 46048 | I52: 7 | J52: 54617.22 | K52: 45787 | L52: UNITED KINGDOM
A53: Resort 1 | B53: 30 days pta | C53: 70805 | D53: 22397.78 | E53: 48407.22 | F53: Deposit Paid | G53: 46042 | H53: 46052 | I53: 10 | J53: 38442.5 | K53: 45971 | L53: Poland
A54: Resort 1 | B54: 30 days pta | C54: 25544 | E54: 25544 | F54: Not paid yet | G54: 46042 | H54: 46048 | I54: 6 | J54: 17109.54 | K54: 45971 | L54: Bulgaria
A55: Resort 1 | B55: 30 days pta | F55: Comp | G55: 46043 | H55: 46047 | I55: 4 | K55: 46002
A56: Resort 1 | B56: 30 days pta | C56: 40086 | E56: 40086 | F56: Not paid yet | G56: 46043 | H56: 46050 | I56: 7 | J56: 19992.21 | K56: 45939 | L56: Germany
A57: Resort 1 | B57: 30 days pta | C57: 0 | E57: 0 | F57: Comp | G57: 46043 | H57: 46050 | I57: 7 | J57: 0 | K57: 45847 | L57: Denmark
A58: Resort 1 | B58: 30 days pta | C58: 17682 | E58: 17682 | F58: Not paid yet | G58: 46043 | H58: 46047 | I58: 4 | J58: 11468.52 | K58: 45896 | L58: United States
A59: Resort 1 | B59: 30 days pta | C59: 22521 | E59: 22521 | F59: Not paid yet | G59: 46043 | H59: 46049 | I59: 6 | J59: 13487.16 | K59: 46000 | L59: Russia
A60: Resort 1 | B60: 30 days pta | C60: 34520 | E60: 34520 | F60: Not paid yet | G60: 46044 | H60: 46049 | I60: 5 | J60: 15066.05 | K60: 45687 | L60: UNITED KINGDOM
A61: Resort 1 | B61: 30 days pta | C61: 18872.48 | D61: 16272.48 | E61: 2600 | F61: Deposit Paid | G61: 46044 | H61: 46047 | I61: 3 | J61: 12065.37 | K61: 45955 | L61: Hong Kong SAR of China
A62: Resort 1 | B62: 30 days pta | C62: 72686 | E62: 72686 | F62: Not paid yet | G62: 46045 | H62: 46052 | I62: 7 | J62: 40194.28 | K62: 45974 | L62: Turkey
A63: Resort 1 | B63: 30 days pta | C63: 12816 | E63: 12816 | F63: Not paid yet | G63: 46045 | H63: 46047 | I63: 2 | J63: 4479.41 | K63: 45989 | L63: China
A64: Resort 1 | B64: 30 days pta | C64: 18947.98 | D64: 18947.98 | F64: Fully Paid | G64: 46046 | H64: 46050 | I64: 4 | J64: 11471.28 | K64: 45785 | L64: France
A65: Resort 1 | B65: 30 days pta | F65: Comp | G65: 46046 | H65: 46052 | I65: 6 | J65: 0 | K65: 45995 | L65: India
A66: Resort 1 | B66: 30 days pta | C66: 19224 | E66: 19224 | F66: Not paid yet | G66: 46047 | H66: 46050 | I66: 3 | J66: 12546.63 | K66: 45989 | L66: China
A67: Resort 1 | B67: 30 days pta | C67: 36837.98 | D67: 18419.2 | E67: 18419.2 | F67: Deposit Paid | G67: 46048 | H67: 46055 | I67: 7 | J67: 22634.29 | K67: 45911 | L67: UNITED KINGDOM
A68: Resort 1 | B68: 30 days pta | C68: 380 | E68: 380 | F68: Not paid yet | G68: 46048 | H68: 46050 | I68: 2 | J68: 0 | K68: 45939 | L68: Germany
A69: Resort 1 | B69: 30 days pta | C69: 73887.5 | D69: 73887.5 | F69: Fully Paid | G69: 46048 | H69: 46055 | I69: 7 | J69: 23605.54 | K69: 45879 | L69: UNITED KINGDOM
A70: Resort 1 | B70: 30 days pta | C70: 0 | E70: 0 | F70: Comp | G70: 46048 | H70: 46059 | I70: 11 | J70: 0 | K70: 45937 | L70: Sweden
A71: Resort 1 | B71: 30 days pta | C71: 397 | E71: 397 | F71: Not paid yet | G71: 46048 | H71: 46051 | I71: 3 | J71: 0 | K71: 45981 | L71: China
A72: Resort 1 | B72: 30 days pta | C72: 1200 | E72: 1200 | F72: Not paid yet | G72: 46048 | H72: 46051 | I72: 3 | J72: 386.91 | K72: 45915 | L72: China
A73: Resort 1 | B73: 30 days pta | C73: 13797 | E73: 13797 | F73: Not paid yet | G73: 46049 | H73: 46051 | I73: 2 | J73: 0 | K73: 45689 | L73: UNITED KINGDOM
A74: Resort 1 | B74: 30 days pta | C74: 0 | E74: 0 | F74: Comp | G74: 46049 | H74: 46073 | I74: 24 | J74: 0 | K74: 45918 | L74: Russia
A75: Resort 1 | B75: 30 days pta | C75: 24252.37 | E75: 24252.37 | F75: Not paid yet | G75: 46049 | H75: 46052 | I75: 3 | J75: 0 | K75: 45966 | L75: UNITED KINGDOM
A76: Resort 1 | B76: 30 days pta | C76: 147338 | D76: 36834.5 | E76: 110503.5 | F76: Deposit Paid | G76: 46050 | H76: 46057 | I76: 7 | J76: 48317.29 | K76: 45967 | L76: Sweden
A77: Resort 1 | B77: 30 days pta | C77: 0 | E77: 0 | F77: Comp | G77: 46050 | H77: 46057 | I77: 7 | J77: 0 | K77: 45935 | L77: UNITED KINGDOM
A78: Resort 1 | B78: 30 days pta | C78: 19395.96 | E78: 19395.96 | F78: Not paid yet | G78: 46051 | H78: 46057 | I78: 6 | J78: 12580.86 | K78: 46000 | L78: UNITED KINGDOM
A79: Resort 1 | B79: 30 days pta | C79: 27320 | E79: 27320 | F79: Not paid yet | G79: 46052 | H79: 46057 | I79: 5 | J79: 17361.1 | K79: 45965 | L79: Germany
A80: Resort 1 | B80: 30 days pta | C80: 325 | E80: 325 | F80: Not paid yet | G80: 46052 | H80: 46054 | I80: 2 | J80: -1144.68 | K80: 45981 | L80: UNITED KINGDOM
A81: Resort 1 | B81: 30 days pta | C81: 8311.2 | E81: 8311.2 | F81: Against VCC | G81: 46052 | H81: 46053 | I81: 1 | J81: 4197.73 | K81: 45986 | L81: Korea (South)
A82: Resort 1 | B82: 30 days pta | C82: 13600 | E82: 13600 | F82: Not paid yet | G82: 46053 | H82: 46067 | I82: 14 | J82: 0 | K82: 45748 | L82: Denmark
A83: Resort 1 | B83: 30 days pta | C83: 35074 | D83: 35074 | F83: Fully Paid | G83: 46053 | H83: 46062 | I83: 9 | J83: 19842.66 | K83: 45849 | L83: Russia
A84: Resort 1 | B84: 30 days pta | C84: 60160 | E84: 60160 | F84: Not paid yet | G84: 46053 | H84: 46062 | I84: 9 | J84: 34232.67 | K84: 45776 | L84: Denmark
A85: Resort 1 | B85: 30 days pta | C85: 35340 | E85: 35340 | F85: Not paid yet | G85: 46053 | H85: 46062 | I85: 9 | J85: 16787.79 | K85: 45776 | L85: Denmark
A86: Resort 1 | B86: 30 days pta | C86: 35340 | E86: 35340 | F86: Not paid yet | G86: 46053 | H86: 46062 | I86: 9 | J86: 16787.79 | K86: 45776 | L86: Denmark
A87: Resort 1 | B87: 30 days pta | C87: 78903.44 | E87: 78903.44 | F87: Not paid yet | G87: 46053 | H87: 46067 | I87: 14 | J87: 54363.82 | K87: 45735 | L87: Denmark
A88: Resort 1 | B88: 30 days pta | C88: 33144 | D88: 17903.79 | E88: 15240.21 | F88: Deposit Paid | G88: 46053 | H88: 46059 | I88: 6 | J88: 19169.76 | K88: 45723 | L88: France
A89: Resort 1 | B89: 30 days pta | C89: 0 | E89: 0 | F89: Comp | G89: 46054 | H89: 46061 | I89: 7 | J89: 0 | K89: 45821 | L89: Russia
A90: Resort 1 | B90: 30 days pta | C90: 26072 | D90: 6518 | E90: 19554 | F90: Deposit Paid | G90: 46054 | H90: 46060 | I90: 6 | J90: 17206.98 | K90: 45984 | L90: Russia
A91: Resort 1 | B91: 30 days pta | C91: 15118 | E91: 15118 | F91: Not paid yet | G91: 46054 | H91: 46061 | I91: 7 | J91: 8616.93 | K91: 45901 | L91: UNITED KINGDOM
A92: Resort 1 | B92: 30 days pta | C92: 38096 | E92: 38096 | F92: Not paid yet | G92: 46055 | H92: 46064 | I92: 9 | J92: 26503.47 | K92: 45926 | L92: UNITED KINGDOM
A93: Resort 1 | B93: 30 days pta | C93: 73887.5 | D93: 73887.5 | F93: Fully Paid | G93: 46055 | H93: 46058 | I93: 3 | J93: 0 | K93: 45879 | L93: UNITED KINGDOM
A94: Resort 1 | B94: 30 days pta | C94: 19688.2 | D94: 4922.05 | E94: 14766.15 | F94: Deposit Paid | G94: 46055 | H94: 46059 | I94: 4 | J94: 13599.04 | K94: 45955 | L94: UNITED KINGDOM
A95: Resort 1 | B95: 30 days pta | C95: 0 | E95: 0 | F95: Comp | G95: 46055 | H95: 46062 | I95: 7 | J95: 0 | K95: 45987 | L95: UNITED KINGDOM
A96: Resort 1 | B96: 30 days pta | C96: 29644 | E96: 29644 | F96: Not paid yet | G96: 46056 | H96: 46062 | I96: 6 | J96: 18974.34 | K96: 45755 | L96: UNITED KINGDOM
A97: Resort 1 | B97: 30 days pta | C97: 900 | E97: 900 | F97: Not paid yet | G97: 46057 | H97: 46059 | I97: 2 | J97: 0 | K97: 45869 | L97: Russia
A98: Resort 1 | B98: 30 days pta | C98: 85090 | D98: 85090 | F98: Fully Paid | G98: 46058 | H98: 46073 | I98: 15 | J98: 51024.45 | K98: 45742 | L98: Netherlands
A99: Resort 1 | B99: 30 days pta | C99: 37015 | E99: 37015 | F99: Not paid yet | G99: 46058 | H99: 46068 | I99: 10 | J99: 13255.6 | K99: 45840 | L99: Denmark
A100: Resort 1 | B100: 30 days pta | C100: 1680 | E100: 1680 | F100: Not paid yet | G100: 46058 | H100: 46082 | I100: 24 | J100: 0 | K100: 45804 | L100: Germany
...

Sheet Resort 2
A1: Resort | B1: Due Date | C1: Invoice Amount | D1: Payment Received | E1: Balance | F1: Payment Status | G1: Arrival | H1: Departure | I1: No of nights | J1: Room Revenue | K1: Date Entered | L1: Country
A2: Resort 2 | B2: 90 days pta | C2: 13788.38 | D2: 13788.38 | F2: Fully Paid | G2: 46023 | H2: 46024 | I2: 1 | J2: 7349.19 | K2: 45912 | L2: Japan
A3: Resort 2 | B3: 90 days pta | C3: 96137.6 | D3: 96137.6 | F3: Fully Paid | G3: 46023 | H3: 46027 | I3: 4 | J3: 66161.16 | K3: 45794 | L3: Japan
A4: Resort 2 | B4: 90 days pta | C4: 79580 | D4: 79580 | F4: Fully Paid | G4: 46023 | H4: 46027 | I4: 4 | J4: 48593.64 | K4: 45724 | L4: United States
A5: Resort 2 | B5: 90 days pta | C5: 31054.8 | D5: 31054.8 | F5: Fully Paid | G5: 46024 | H5: 46028 | I5: 4 | J5: 21277.4 | K5: 45699 | L5: United States
A6: Resort 2 | B6: 90 days pta | C6: 142945.63 | D6: 142945.63 | F6: Fully Paid | G6: 46025 | H6: 46032 | I6: 7 | J6: 81000.78 | K6: 45978 | L6: Spain
A7: Resort 2 | B7: 90 days pta | C7: 104286 | D7: 104286 | F7: Fully Paid | G7: 46026 | H7: 46033 | I7: 7 | J7: 76173.3 | K7: 45953 | L7: United States
A8: Resort 2 | B8: 90 days pta | C8: 108000 | D8: 108000 | F8: Fully Paid | G8: 46026 | H8: 46034 | I8: 8 | J8: 77793.28 | K8: 45982 | L8: Russia
A9: Resort 2 | B9: 90 days pta | C9: 64812.48 | D9: 64812.48 | F9: Fully Paid | G9: 46029 | H9: 46033 | I9: 4 | J9: 56040.44 | K9: 45978 | L9: Unknown
A10: Resort 2 | B10: 90 days pta | C10: 100000 | D10: 25187.52 | E10: 74812.487 | F10: Deposit Paid | G10: 46029 | H10: 46033 | I10: 4 | J10: 55927.52 | K10: 45978 | L10: Unknown
A11: Resort 2 | B11: 30 days pta | C11: 34931.98 | D11: 34931.98 | F11: Fully Paid | G11: 46029 | H11: 46036 | I11: 7 | J11: 22855.49 | K11: 45824 | L11: Russia
A12: Resort 2 | B12: 30 days pta | C12: 53611.66 | E12: 53611.66 | F12: Not paid yet | G12: 46029 | H12: 46043 | I12: 14 | J12: 32521.86 | K12: 45999 | L12: UNITED KINGDOM
A13: Resort 2 | B13: 30 days pta | C13: 54341.6 | D13: 54341.6 | F13: Fully Paid | G13: 46029 | H13: 46034 | I13: 5 | J13: 28503.95 | K13: 45938 | L13: Australia
A14: Resort 2 | B14: 30 days pta | C14: 28757.12 | D14: 28757.12 | F14: Fully Paid | G14: 46030 | H14: 46034 | I14: 4 | J14: 20483.16 | K14: 45962 | L14: Japan
A15: Resort 2 | B15: 30 days pta | C15: 44845.14 | D15: 44845.14 | F15: Fully Paid | G15: 46031 | H15: 46038 | I15: 7 | J15: 28744.73 | K15: 45721 | L15: United States
A16: Resort 2 | B16: 30 days pta | C16: 63370.87 | D16: 63370.87 | F16: Fully Paid | G16: 46032 | H16: 46039 | I16: 7 | J16: 42746.34 | K16: 45992 | L16: Brazil
A17: Resort 2 | B17: 30 days pta | C17: 27132 | D17: 27132 | F17: Fully Paid | G17: 46033 | H17: 46038 | I17: 5 | J17: 16744.5 | K17: 45918 | L17: Brazil
A18: Resort 2 | B18: 30 days pta | C18: 19220 | D18: 19220 | F18: Fully Paid | G18: 46033 | H18: 46038 | I18: 5 | J18: 12315.45 | K18: 45947 | L18: Canada
A19: Resort 2 | B19: 30 days pta | C19: 24522.32 | D19: 24522.32 | F19: Fully Paid | G19: 46033 | H19: 46040 | I19: 7 | J19: 15906.81 | K19: 45967 | L19: United States
A20: Resort 2 | B20: 30 days pta | C20: 31975.68 | D20: 31975.68 | F20: Credit Facility | G20: 46033 | H20: 46037 | I20: 4 | J20: 18803.16 | K20: 45919 | L20: UNITED KINGDOM
A21: Resort 2 | B21: 30 days pta | C21: 77066 | E21: 77066 | F21: Not paid yet | G21: 46034 | H21: 46041 | I21: 7 | J21: 53197.48 | K21: 45702 | L21: Australia
A22: Resort 2 | B22: 30 days pta | F22: Tentative | G22: 46034 | H22: 46038 | I22: 4 | J22: 10531.12 | K22: 45998 | L22: China
A23: Resort 2 | B23: 30 days pta | F23: Tentative | G23: 46034 | H23: 46038 | I23: 4 | J23: 10531.12 | K23: 46000 | L23: China
A24: Resort 2 | B24: 30 days pta | C24: 5402.98 | E24: 5402.98 | F24: Against VCC | G24: 46034 | H24: 46035 | I24: 1 | J24: 2021.5 | K24: 45996
A25: Resort 2 | B25: 30 days pta | C25: 92486 | E25: 92486 | F25: Not paid yet | G25: 46034 | H25: 46041 | I25: 7 | J25: 66948.98 | K25: 45654 | L25: Australia
A26: Resort 2 | B26: 30 days pta | C26: 32887.3 | E26: 32887.3 | F26: Not paid yet | G26: 46034 | H26: 46041 | I26: 7 | J26: 22290.31 | K26: 45702 | L26: Australia
A27: Resort 2 | B27: 30 days pta | C27: 32887.25 | E27: 32887.25 | F27: Not paid yet | G27: 46034 | H27: 46041 | I27: 7 | J27: 22290.31 | K27: 45707 | L27: Australia
A28: Resort 2 | B28: 30 days pta | C28: 23719.16 | D28: 23719.16 | F28: Fully Paid | G28: 46035 | H28: 46040 | I28: 5 | J28: 15529.6 | K28: 45986 | L28: France
A29: Resort 2 | B29: 30 days pta | C29: 10491.53 | E29: 10491.53 | F29: Not paid yet | G29: 46035 | H29: 46042 | I29: 7 | J29: 0 | K29: 45895 | L29: Unknown
A30: Resort 2 | B30: 30 days pta | C30: 16044 | D30: 4011 | E30: 12033 | F30: Deposit Paid | G30: 46035 | H30: 46039 | I30: 4 | J30: 7379.42 | K30: 45973 | L30: China
A31: Resort 2 | B31: 30 days pta | C31: 16744 | D31: 4186 | E31: 12558 | F31: Deposit Paid | G31: 46035 | H31: 46039 | I31: 4 | J31: 7913.62 | K31: 45975 | L31: China
A32: Resort 2 | B32: 30 days pta | C32: 12547.66 | E32: 12547.66 | F32: Not paid yet | G32: 46036 | H32: 46038 | I32: 2 | J32: 6211.58 | K32: 45980 | L32: Macau - SAR of China
A33: Resort 2 | B33: 30 days pta | C33: 14276 | D33: 3569 | E33: 10707 | F33: Deposit Paid | G33: 46036 | H33: 46040 | I33: 4 | J33: 8593.64 | K33: 45947 | L33: China
A34: Resort 2 | B34: 30 days pta | C34: 28288.4 | E34: 28288.4 | F34: Not paid yet | G34: 46036 | H34: 46043 | I34: 7 | J34: 17820.46 | K34: 45902 | L34: Canada
A35: Resort 2 | B35: 30 days pta | C35: 13655.36 | D35: 11055.36 | E35: 2600 | F35: Deposit Paid | G35: 46036 | H35: 46038 | I35: 2 | J35: 8201.58 | K35: 45939 | L35: Chinese Taiwan
A36: Resort 2 | B36: 30 days pta | C36: 15446 | D36: 3861 | E36: 11585 | F36: Deposit Paid | G36: 46036 | H36: 46040 | I36: 4 | J36: 7577.84 | K36: 45969 | L36: China
A37: Resort 2 | B37: 30 days pta | C37: 102038.43 | D37: 102038.43 | F37: Fully Paid | G37: 46037 | H37: 46044 | I37: 7 | J37: 75122.46 | K37: 45980 | L37: Australia
A38: Resort 2 | B38: 30 days pta | C38: 61778.72 | D38: 9542.5 | E38: 52236.22 | F38: Deposit Paid | G38: 46037 | H38: 46044 | I38: 7 | J38: 39983.79 | K38: 45944 | L38: Australia
A39: Resort 2 | B39: 30 days pta | C39: 23095 | E39: 23095 | F39: Not paid yet | G39: 46037 | H39: 46042 | I39: 5 | J39: 0 | K39: 45984 | L39: Kazakhstan
A40: Resort 2 | G40: 46037 | H40: 46041 | I40: 4
A41: Resort 2 | G41: 46037 | H41: 46041 | I41: 4
A42: Resort 2 | B42: 30 days pta | C42: 31998.34 | D42: 16144.25 | E42: 15854.09 | F42: Not paid yet | G42: 46038 | H42: 46042 | I42: 4 | J42: 15129.9 | K42: 45860 | L42: Netherlands
A43: Resort 2 | B43: 30 days pta | C43: 25216 | E43: 25216 | F43: Not paid yet | G43: 46038 | H43: 46042 | I43: 4 | J43: 13557.12 | K43: 45567 | L43: Brazil
A44: Resort 2 | B44: 30 days pta | C44: 23719.15 | E44: 23719.15 | F44: Not paid yet | G44: 46038 | H44: 46043 | I44: 5 | J44: 15528.95 | K44: 45994 | L44: Thailand
A45: Resort 2 | G45: 46038 | H45: 46042 | I45: 4
A46: Resort 2 | G46: 46038 | H46: 46042 | I46: 4
A47: Resort 2 | B47: 30 days pta | C47: 50000 | E47: 50000 | F47: Not paid yet | G47: 46039 | H47: 46049 | I47: 10 | J47: 16208.2 | K47: 45982 | L47: Russia
A48: Resort 2 | B48: 30 days pta | C48: 24538 | E48: 24538 | F48: Not paid yet | G48: 46039 | H48: 46046 | I48: 7 | J48: 13247.85 | K48: 45962 | L48: UNITED KINGDOM
A49: Resort 2 | B49: 30 days pta | C49: 864 | E49: 864 | F49: Not paid yet | G49: 46039 | H49: 46057 | I49: 18 | J49: 329.76 | K49: 45753 | L49: Germany
A50: Resort 2 | B50: 30 days pta | C50: 77128.99 | E50: 77128.99 | F50: Not paid yet | G50: 46039 | H50: 46046 | I50: 7 | J50: 52957.1 | K50: 45910 | L50: Australia
A51: Resort 2 | B51: 30 days pta | C51: 19506 | E51: 19506 | F51: Not paid yet | G51: 46039 | H51: 46043 | I51: 4 | J51: 10549.44 | K51: 45907 | L51: Unknown
A52: Resort 2 | B52: 30 days pta | C52: 6117.83 | E52: 6117.83 | F52: Not paid yet | G52: 46040 | H52: 46041 | I52: 1 | J52: 2567.03 | K52: 45980 | L52: Japan
A53: Resort 2 | B53: 30 days pta | C53: 33872.8 | D53: 8468.2 | E53: 25404.6 | F53: Deposit Paid | G53: 46040 | H53: 46046 | I53: 6 | J53: 19725.84 | K53: 45921 | L53: UNITED KINGDOM
A54: Resort 2 | B54: 30 days pta | C54: 18212.14 | E54: 18212.14 | F54: Against VCC | G54: 46040 | H54: 46047 | I54: 7 | J54: 12494.79 | K54: 45986 | L54: United States
A55: Resort 2 | B55: 30 days pta | C55: 17402 | D55: 4350.5 | E55: 13051.5 | F55: Deposit Paid | G55: 46041 | H55: 46045 | I55: 4 | J55: 7760.98 | K55: 45965 | L55: China
A56: Resort 2 | B56: 30 days pta | C56: 33278.76 | E56: 33278.76 | F56: Not paid yet | G56: 46041 | H56: 46048 | I56: 7 | J56: 22515.81 | K56: 45827 | L56: Ireland
A57: Resort 2 | B57: 30 days pta | C57: 12872 | E57: 12872 | F57: Not paid yet | G57: 46042 | H57: 46045 | I57: 3 | J57: 6456.87 | K57: 45966 | L57: Korea (South)
A58: Resort 2 | B58: 30 days pta | C58: 720 | E58: 720 | F58: Not paid yet | G58: 46043 | H58: 46058 | I58: 15 | J58: 0 | K58: 45888 | L58: Unknown
A59: Resort 2 | B59: 30 days pta | C59: 26592 | E59: 26592 | F59: Not paid yet | G59: 46043 | H59: 46046 | I59: 3 | J59: 13543.11 | K59: 45933 | L59: Argentina
A60: Resort 2 | B60: 30 days pta | C60: 95980.8 | E60: 95980.8 | F60: Not paid yet | G60: 46043 | H60: 46053 | I60: 10 | J60: 67315.44 | K60: 45889 | L60: UNITED KINGDOM
A61: Resort 2 | B61: 30 days pta | C61: 26617.68 | D61: 26617.68 | F61: Fully Paid | G61: 46044 | H61: 46048 | I61: 4 | J61: 10227.16 | K61: 45995 | L61: United States
A62: Resort 2 | B62: 30 days pta | C62: 0 | E62: 0 | F62: Comp | G62: 46044 | H62: 46048 | I62: 4 | J62: 0 | K62: 45977 | L62: India
A63: Resort 2 | B63: 30 days pta | C63: 20000 | E63: 20000 | F63: Not paid yet | G63: 46045 | H63: 46047 | I63: 2 | J63: 11212.6 | K63: 45995 | L63: India
A64: Resort 2 | B64: 30 days pta | C64: 0 | E64: 0 | F64: Comp | G64: 46045 | H64: 46048 | I64: 3 | J64: -915.76 | K64: 45836
A65: Resort 2 | B65: 30 days pta | C65: 0 | E65: 0 | F65: Comp | G65: 46045 | H65: 46048 | I65: 3 | J65: -915.76 | K65: 45836
A66: Resort 2 | G66: 46046 | H66: 46051 | I66: 5
A67: Resort 2 | B67: 30 days pta | C67: 94816.14 | D67: 23705 | E67: 71111.14 | F67: Deposit Paid | G67: 46046 | H67: 46052 | I67: 6 | J67: 54224.76 | K67: 45954 | L67: Turkey
A68: Resort 2 | B68: 30 days pta | C68: 0 | E68: 0 | F68: Tentative | G68: 46046 | H68: 46051 | I68: 5 | J68: 13345 | K68: 46001 | L68: China
A69: Resort 2 | B69: 30 days pta | C69: 11008.94 | E69: 11008.94 | F69: Against VCC | G69: 46046 | H69: 46049 | I69: 3 | J69: 6064.5 | K69: 45995 | L69: Korea (South)
A70: Resort 2 | B70: 30 days pta | C70: 302 | E70: 302 | F70: Payment on Arrival | G70: 46046 | H70: 46048 | I70: 2 | J70: 0 | K70: 45955 | L70: China
A71: Resort 2 | B71: 30 days pta | C71: 1556 | E71: 1556 | F71: Not paid yet | G71: 46046 | H71: 46048 | I71: 2 | J71: 257.94 | K71: 45985 | L71: China
A72: Resort 2 | B72: 30 days pta | C72: 15806.4 | D72: 3899.1 | E72: 11907.3 | F72: Deposit Paid | G72: 46047 | H72: 46052 | I72: 5 | J72: 8959.1 | K72: 45966 | L72: Unknown
A73: Resort 2 | B73: 30 days pta | C73: 24288.74 | E73: 24288.74 | F73: Not paid yet | G73: 46047 | H73: 46049 | I73: 2 | J73: 14485.46 | K73: 45995 | L73: India
A74: Resort 2 | B74: 30 days pta | C74: 23790 | E74: 23790 | F74: Not paid yet | G74: 46047 | H74: 46052 | I74: 5 | J74: 15967.35 | K74: 45896 | L74: United States
A75: Resort 2 | B75: 30 days pta | C75: 12572 | E75: 12572 | F75: Not paid yet | G75: 46047 | H75: 46050 | I75: 3 | J75: 7389.27 | K75: 45976 | L75: India
A76: Resort 2 | B76: 30 days pta | C76: 27122 | E76: 27122 | F76: Not paid yet | G76: 46047 | H76: 46056 | I76: 9 | J76: 16239.33 | K76: 45953 | L76: China
A77: Resort 2 | B77: 30 days pta | C77: 8677 | D77: 4351 | E77: 4326 | F77: Deposit Paid | G77: 46047 | H77: 46049 | I77: 2 | J77: 2835.01 | K77: 45962 | L77: China
A78: Resort 2 | B78: 30 days pta | C78: 24208 | E78: 24208 | F78: Not paid yet | G78: 46048 | H78: 46053 | I78: 5 | J78: 12027.95 | K78: 45668 | L78: UNITED KINGDOM
A79: Resort 2 | B79: 30 days pta | C79: 13113.26 | E79: 13113.26 | F79: Not paid yet | G79: 46048 | H79: 46051 | I79: 3 | J79: 9317.37 | K79: 45952 | L79: Australia
A80: Resort 2 | B80: 30 days pta | C80: 33693.52 | E80: 33693.52 | F80: Not paid yet | G80: 46049 | H80: 46056 | I80: 7 | J80: 23605.54 | K80: 45888 | L80: UNITED KINGDOM
A81: Resort 2 | B81: 30 days pta | C81: 19162.64 | E81: 19162.64 | F81: Not paid yet | G81: 46049 | H81: 46052 | I81: 3 | J81: 12286.79 | K81: 45907 | L81: United Arab Emirates
A82: Resort 2 | B82: 30 days pta | C82: 8677 | E82: 8677 | F82: Not paid yet | G82: 46049 | H82: 46051 | I82: 2 | J82: 3063.94 | K82: 45962 | L82: China
A83: Resort 2 | B83: 30 days pta | C83: 325 | E83: 325 | F83: Payment on Arrival | G83: 46050 | H83: 46052 | I83: 2 | J83: 0 | K83: 45981 | L83: UNITED KINGDOM
A84: Resort 2 | B84: 30 days pta | C84: 0 | E84: 0 | F84: Comp | G84: 46050 | H84: 46052 | I84: 2 | J84: 0 | K84: 45939 | L84: Germany
A85: Resort 2 | B85: 30 days pta | C85: 11232.35 | D85: 11232.35 | F85: Fully Paid | G85: 46050 | H85: 46053 | I85: 3 | J85: 6082.38 | K85: 45785 | L85: France
A86: Resort 2 | B86: 30 days pta | C86: 33600 | E86: 33600 | F86: Not paid yet | G86: 46051 | H86: 46056 | I86: 5 | J86: 14786.3 | K86: 45689 | L86: UNITED KINGDOM
A87: Resort 2 | B87: 30 days pta | C87: 23747.6 | D87: 5286.9 | E87: 18460.7 | F87: Deposit Paid | G87: 46051 | H87: 46056 | I87: 5 | J87: 12688.95 | K87: 45964 | L87: Korea (South)
A88: Resort 2 | B88: 30 days pta | C88: 15099.44 | D88: 3774.86 | E88: 11324.58 | F88: Deposit Paid | G88: 46051 | H88: 46055 | I88: 4 | J88: 10133.88 | K88: 45955 | L88: UNITED KINGDOM
A89: Resort 2 | B89: 30 days pta | C89: 44593.66 | E89: 44593.66 | F89: Not paid yet | G89: 46051 | H89: 46068 | I89: 17 | J89: 29403.03 | K89: 45992 | L89: Ukraine
A90: Resort 2 | B90: 30 days pta | C90: 29960.95 | D90: 7490.23 | E90: 22470.72 | F90: Deposit Paid | G90: 46053 | H90: 46060 | I90: 7 | J90: 19283.39 | K90: 45971 | L90: Germany
A91: Resort 2 | B91: 30 days pta | C91: 74312 | E91: 74312 | F91: Not paid yet | G91: 46053 | H91: 46069 | I91: 16 | J91: 52844.96 | K91: 45850 | L91: UNITED KINGDOM
A92: Resort 2 | B92: 30 days pta | C92: 5720.95 | E92: 5720.95 | F92: Not paid yet | G92: 46053 | H92: 46054 | I92: 1 | J92: 2305.32 | K92: 45986 | L92: China
A93: Resort 2 | B93: 30 days pta | C93: 2600 | E93: 2600 | F93: Not paid yet | G93: 46053 | H93: 46060 | I93: 7 | J93: 0 | K93: 45927 | L93: Denmark
A94: Resort 2 | B94: 30 days pta | C94: 9004 | E94: 9004 | F94: Not paid yet | G94: 46053 | H94: 46055 | I94: 2 | J94: 0 | K94: 45985 | L94: China
A95: Resort 2 | B95: 30 days pta | C95: 5025 | E95: 5025 | F95: Payment on Arrival | G95: 46054 | H95: 46060 | I95: 6 | J95: -482.28 | K95: 45847 | L95: UNITED KINGDOM
A96: Resort 2 | B96: 30 days pta | C96: 20779.52 | D96: 20779.52 | F96: Fully Paid | G96: 46054 | H96: 46058 | I96: 4 | J96: 13329.9 | K96: 45895 | L96: Australia
A97: Resort 2 | B97: 30 days pta | C97: 19942 | D97: 4570.5 | E97: 15371.5 | F97: Deposit Paid | G97: 46054 | H97: 46058 | I97: 4 | J97: 6982.61 | K97: 45973 | L97: China
A98: Resort 2 | B98: 30 days pta | C98: 26038.28 | D98: 6509.57 | E98: 19528.71 | F98: Deposit Paid | G98: 46055 | H98: 46061 | I98: 6 | J98: 13747.14 | K98: 45992 | L98: Singapore
A99: Resort 2 | B99: 30 days pta | C99: 13506 | E99: 13506 | F99: Not paid yet | G99: 46055 | H99: 46058 | I99: 3 | J99: 5366.31 | K99: 45984 | L99: China
A100: Resort 2 | B100: 30 days pta | C100: 15496 | D100: 3874 | E100: 11622 | F100: Deposit Paid | G100: 46057 | H100: 46061 | I100: 4 | J100: 7615.99 | K100: 45993 | L100: China
...

Sheet Resort 3
A1: Resort | B1: Due Date | C1: Invoice Amount | D1: Payment Received | E1: Balance | F1: Payment Status | G1: Arrival | H1: Departure | I1: No of nights | J1: Opera Status | K1: Date Entered | L1: Country
A2: Resort 3 | B2: 90 days pta | C2: 0 | E2: 0 | F2: Comp | G2: 46024 | H2: 46026 | I2: 2 | J2: COG | K2: 45972 | L2: United Arab Emirates
A3: Resort 3 | B3: 90 days pta | C3: 18133.32 | D3: 18133.32 | F3: Fully Paid | G3: 46025 | H3: 46028 | I3: 3 | J3: DPR | K3: 45974 | L3: Germany
A4: Resort 3 | B4: 30 days pta | C4: 47826 | D4: 47826 | F4: Fully Paid | G4: 46034 | H4: 46036 | I4: 2 | J4: DPR | K4: 45976 | L4: Saudi Arabia
A5: Resort 3 | B5: 30 days pta | C5: 26896.8 | D5: 6724.2 | E5: 20172.6 | F5: Deposit paid | G5: 46035 | H5: 46037 | I5: 2 | J5: DPR | K5: 45957 | L5: United States
A6: Resort 3 | B6: 30 days pta | C6: 39274.86 | D6: 30664.86 | E6: 8610 | F6: Deposit paid | G6: 46035 | H6: 46038 | I6: 3 | J6: DPR | K6: 45963 | L6: United States
A7: Resort 3 | B7: 30 days pta | C7: 99261.62 | E7: 99261.62 | F7: Not paid yet | G7: 46035 | H7: 46042 | I7: 7 | J7: NOG | K7: 45859 | L7: United States
A8: Resort 3 | B8: 30 days pta | C8: 0 | E8: 0 | F8: Comp | G8: 46041 | H8: 46043 | I8: 2 | J8: COG | K8: 45954 | L8: China
A9: Resort 3 | B9: 30 days pta | C9: 62200 | D9: 62200 | F9: Fully Paid | G9: 46045 | H9: 46051 | I9: 6 | J9: DPR | K9: 45588 | L9: United States
A10: Resort 3 | B10: 30 days pta | F10: Comp | G10: 46047 | H10: 46050 | J10: TENT
A11: Resort 3 | B11: 30 days pta | C11: 50914 | E11: 50914 | F11: Not paid yet | G11: 46048 | H11: 46050 | I11: 2 | J11: TOG | K11: 45748 | L11: Japan
A12: Resort 3 | B12: 30 days pta | C12: 33377.37 | E12: 33377.37 | F12: Not paid yet | G12: 46050 | H12: 46053 | I12: 3 | J12: TENT | K12: 45988 | L12: United States
A13: Resort 3 | B13: 30 days pta | C13: 26559.98 | D13: 26559.98 | F13: Fully Paid | G13: 46052 | H13: 46059 | I13: 7 | J13: DPR | K13: 45803 | L13: Russia
A14: Resort 3 | B14: 30 days pta | C14: 3942 | E14: 3942 | F14: Not paid yet | G14: 46052 | H14: 46054 | I14: 2 | J14: COG | K14: 45939 | L14: Germany
A15: Resort 3 | B15: 30 days pta | C15: 77770.06 | D15: 15692.64 | E15: 62077.42 | F15: Deposit paid | G15: 46057 | H15: 46065 | I15: 8 | J15: DPR | K15: 45812 | L15: United States
A16: Resort 3 | B16: 30 days pta | C16: 575 | E16: 575 | F16: Payment on Arrival | G16: 46059 | H16: 46061 | I16: 2 | J16: COG | K16: 45869 | L16: Russia
A17: Resort 3 | B17: 30 days pta | C17: 18948 | D17: 5684.4 | E17: 13263.6 | F17: Deposit paid | G17: 46063 | H17: 46065 | I17: 2 | J17: DPR | K17: 45951 | L17: Brazil
A18: Resort 3 | B18: 30 days pta | C18: 0 | E18: 0 | F18: Comp | G18: 46067 | H18: 46070 | I18: 3 | J18: COG | K18: 45989 | L18: UNITED KINGDOM
A19: Resort 3 | B19: 30 days pta | C19: 21328.5 | E19: 21328.5 | F19: Not paid yet | G19: 46067 | H19: 46070 | I19: 3 | J19: NOG | K19: 45446 | L19: UNITED KINGDOM
A20: Resort 3 | B20: 30 days pta | C20: 15001.26 | E20: 15001.26 | F20: Not paid yet | G20: 46068 | H20: 46070 | I20: 2 | J20: NOG | K20: 45885 | L20: United States
A21: Resort 3 | B21: 30 days pta | C21: 36994 | D21: 9248.5 | E21: 27745.5 | F21: Deposit paid | G21: 46068 | H21: 46072 | I21: 4 | J21: DPR | K21: 45967 | L21: China
A22: Resort 3 | B22: 30 days pta | C22: 0 | E22: 0 | F22: Comp | G22: 46071 | H22: 46073 | I22: 2 | J22: COG | K22: 46001 | L22: Saudi Arabia
A23: Resort 3 | B23: 30 days pta | C23: 45555 | D23: 45555 | F23: Fully Paid | G23: 46071 | H23: 46076 | I23: 5 | J23: DPR | K23: 45972 | L23: United Arab Emirates
A24: Resort 3 | B24: 30 days pta | C24: 35046 | E24: 35046 | F24: Not paid yet | G24: 46071 | H24: 46075 | I24: 4 | J24: NOG | K24: 45989 | L24: China
A25: Resort 3 | B25: 30 days pta | C25: 3900 | D25: 3900 | F25: Fully Paid | G25: 46072 | H25: 46073 | I25: 1 | J25: DPR | K25: 45883 | L25: China
A26: Resort 3 | B26: 30 days pta | C26: 334000.04 | D26: 334000.04 | F26: Fully Paid | G26: 46077 | H26: 46091 | I26: 14 | J26: DPR | K26: 45939 | L26: United Arab Emirates
A27: Resort 3 | B27: 30 days pta | C27: 1150 | E27: 1150 | F27: Not paid yet | G27: 46086 | H27: 46087 | I27: 1 | J27: NOG | K27: 45717 | L27: UNITED KINGDOM
A28: Resort 3 | B28: 30 days pta | C28: 28270 | E28: 28270 | F28: Not paid yet | G28: 46087 | H28: 46092 | I28: 5 | J28: NOG | K28: 45877 | L28: Germany
A29: Resort 3 | B29: 30 days pta | C29: 56549.5 | E29: 56549.5 | F29: Not paid yet | G29: 46089 | H29: 46096 | I29: 7 | J29: DPR | K29: 45987 | L29: Austria
A30: Resort 3 | B30: 30 days pta | C30: 136903.07 | D30: 136903.07 | F30: Fully Paid | G30: 46096 | H30: 46110 | I30: 14 | J30: DPR | K30: 45761 | L30: Germany
A31: Resort 3 | B31: 30 days pta | C31: 56091 | E31: 56091 | F31: Not paid yet | G31: 46097 | H31: 46106 | I31: 9 | J31: NOG | K31: 45828 | L31: Germany
A32: Resort 3 | B32: 30 days pta | C32: 0 | E32: 0 | F32: Comp | G32: 46098 | H32: 46100 | I32: 2 | J32: COG | K32: 45799 | L32: United States
A33: Resort 3 | B33: 30 days pta | C33: 0 | E33: 0 | F33: Comp | G33: 46098 | H33: 46100 | I33: 2 | J33: COG | K33: 45989 | L33: UNITED KINGDOM
A34: Resort 3 | B34: 30 days pta | G34: 46099 | H34: 46104 | J34: TEN
A35: Resort 3 | B35: 30 days pta | G35: 46099 | H35: 46104 | J35: TEN
A36: Resort 3 | B36: 30 days pta | C36: 56981.2 | D36: 32227.01 | E36: 24754.19 | F36: Deposit paid | G36: 46100 | H36: 46110 | I36: 10 | J36: DPR | K36: 45775 | L36: Slovakia
A37: Resort 3 | B37: 30 days pta | C37: 91374 | E37: 91374 | F37: Not paid yet | G37: 46109 | H37: 46118 | I37: 9 | J37: NOG | K37: 45958 | L37: Spain
A38: Resort 3 | B38: 30 days pta | C38: 75860 | E38: 75860 | F38: Not paid yet | G38: 46110 | H38: 46117 | I38: 7 | J38: NOG | K38: 45800 | L38: UNITED KINGDOM
A39: Resort 3 | B39: 30 days pta | C39: 86700 | E39: 86700 | F39: Not paid yet | G39: 46110 | H39: 46117 | I39: 7 | J39: NOG | K39: 45800 | L39: UNITED KINGDOM
A40: Resort 3 | B40: 30 days pta | C40: 51524.6 | D40: 14095.89 | E40: 37428.71 | F40: Deposit paid | G40: 46112 | H40: 46117 | I40: 5 | J40: DPR | K40: 45833 | L40: UNITED KINGDOM
A41: Resort 3 | B41: 30 days pta | C41: 36312.18 | E41: 36312.18 | F41: Not paid yet | G41: 46115 | H41: 46118 | I41: 3 | J41: NOG | K41: 45786 | L41: Italy
A42: Resort 3 | B42: 30 days pta | C42: 67386 | E42: 67386 | F42: Not paid yet | G42: 46124 | H42: 46131 | I42: 7 | J42: TENT | K42: 45905 | L42: Unknown
A43: Resort 3 | B43: 30 days pta | C43: 26248 | E43: 26248 | F43: Not paid yet | G43: 46134 | H43: 46137 | I43: 3 | J43: NOG | K43: 45927 | L43: UNITED KINGDOM
A44: Resort 3 | B44: 30 days pta | C44: 19186.22 | E44: 19186.22 | F44: Not paid yet | G44: 46134 | H44: 46137 | I44: 3 | J44: NOG | K44: 45715 | L44: Switzerland
A45: Resort 3 | B45: 30 days pta | C45: 0 | E45: 0 | F45: Comp | G45: 46140 | H45: 46143 | I45: 3 | J45: NOG | K45: 45834 | L45: UNITED KINGDOM
A46: Resort 3 | B46: 30 days pta | C46: 18996 | E46: 18996 | F46: Not paid yet | G46: 46146 | H46: 46150 | I46: 4 | J46: TENT | K46: 45999 | L46: China
A47: Resort 3 | B47: 30 days pta | F47: Tentative | G47: 46147 | H47: 46151 | I47: 4 | J47: TENT | K47: 45999 | L47: China
A48: Resort 3 | B48: 30 days pta | C48: 1075 | E48: 1075 | F48: Not paid yet | G48: 46149 | H48: 46151 | I48: 2 | J48: COG | K48: 45911 | L48: UNITED KINGDOM
A49: Resort 3 | B49: 30 days pta | C49: 21017.97 | E49: 21017.97 | F49: Not paid yet | G49: 46151 | H49: 46155 | I49: 4 | J49: NOG | K49: 45815 | L49: United States
A50: Resort 3 | B50: 30 days pta | C50: 20914 | E50: 20914 | F50: Not paid yet | G50: 46151 | H50: 46155 | I50: 4 | J50: NOG | K50: 45835 | L50: Singapore
A51: Resort 3 | B51: 30 days pta | C51: 28817.97 | E51: 28817.97 | F51: Not paid yet | G51: 46164 | H51: 46171 | I51: 7 | J51: NOG | K51: 45998 | L51: United States
A52: Resort 3 | B52: 30 days pta | C52: 29074.85 | E52: 29074.85 | F52: Not paid yet | G52: 46166 | H52: 46171 | I52: 5 | J52: NOG | K52: 45968 | L52: United States
A53: Resort 3 | B53: 30 days pta | C53: 0 | E53: 0 | F53: Comp | G53: 46179 | H53: 46180 | I53: 1 | J53: NOG | K53: 45999 | L53: Singapore
A54: Resort 3 | B54: 30 days pta | C54: 24842 | E54: 24842 | F54: Not paid yet | G54: 46242 | H54: 46244 | I54: 2 | J54: NOG | K54: 45983 | L54: China
A55: Resort 3 | B55: 30 days pta | C55: 0 | E55: 0 | F55: Comp | G55: 46262 | H55: 46264 | I55: 2 | J55: COG | K55: 45961 | L55: China
A56: Resort 3 | B56: 30 days pta | C56: 29522.66 | D56: 29522.66 | F56: Fully Paid | G56: 46352 | H56: 46356 | I56: 4 | J56: DPR | K56: 45854 | L56: Do Not Use
A57: Resort 3 | B57: 30 days pta | C57: 43700 | D57: 43700 | F57: Fully Paid | G57: 46361 | H57: 46368 | I57: 7 | J57: DPR | K57: 45931 | L57: Singapore
